Workbook

Sheet Read Me
A1: UAE B2B AUTOMOTIVE & FLEET SALES INTELLIGENCE ENGINE
A2: Commercial decision-support system | ALL DATA IS SYNTHETIC | As-of 30 June 2026
A4: SECTION | B4: CONTENT
A5: Purpose | B5: Integrated decision-support system for a UAE fleet/automotive dealer: scores leads, predicts customer churn, quantifies revenue at risk, surfaces fleet renewal/upgrade opportunities, diagnoses the sales funnel and ranks marketing sources by return.
A6: Data disclaimer | B6: 100% SYNTHETIC data generated from a seeded latent-driver model. No real company, person, contract or transaction is represented. Values in AED unless labelled USD.
A7: Scope | B7: 2,000 leads | 720 active accounts | 11,397 sales activities | 4,251 service records.
A8: Lead scoring model | B8: Logistic Regression vs Random Forest, trained on closed leads only (Won/Lost). Champion: Logistic Regression (test ROC-AUC 0.824). Output: conversion probability 0-100 plus a priority band.
A9: Churn model | B9: Logistic Regression vs Random Forest on contract, spend, engagement and service-health features. Champion: Random Forest (test ROC-AUC 0.737), threshold tuned for recall.
A10: Leakage control | B10: Post-outcome fields (Sales_Stage, Conversion_Date, Sales_Cycle_Days, Lost_Reason, Churn_Status) are excluded from features. Stratified train/test split with 5-fold CV; train and test AUC are both reported so overfitting is visible.
A11: Revenue at Risk | B11: Revenue_at_Risk = Annual_Spend x Churn_Probability. A deterministic exposure measure that ranks retention effort by money rather than by probability alone.
A12: Risk bands | B12: Critical: churn >70% and spend >AED 200k | High: >50% and spend >AED 100k | Medium: 30-50% | Low: <30%.
A13: Fleet opportunities | B13: Renewal = contract expiring within 90 days. Upgrade = fleet >10 units with no purchase in 3+ years. Cross-sell = 50%+ YoY spend growth. Ranked by an urgency score blending account value, expiry proximity and churn probability.
A14: Weighted pipeline | B14: Open deal value x stage win probability (Prospect 10%, Qualified 25%, Proposal 45%, Negotiation 70%).
A15: Funnel assumption | B15: For a lost deal the furthest stage reached is inferred from the loss reason: price/competitor = Negotiation, spec mismatch = Proposal, timing deferred = Qualified, no decision = Prospect.
... A18: Rebuild | B18: python scripts/01_generate_data.py, then 02 -> 03 -> 04 -> 05 -> 06. Interactive dashboard: streamlit run app.py
A21: Data quality log (from 02_eda_validation.py)
A22: severity | B22: table | C22: issue
A23: INFO | B23: leads | C23: 2,000 rows, 25 columns
A24: OK | B24: leads | C24: duplicate Lead_ID: 0
A25: OK | B25: leads | C25: no unexpected missing values
A26: INFO | B26: accounts | C26: 720 rows, 29 columns
A27: OK | B27: accounts | C27: duplicate Account_ID: 0
A28: OK | B28: accounts | C28: no unexpected missing values
A29: INFO | B29: activities | C29: 11,397 rows, 9 columns
A30: OK | B30: activities | C30: duplicate Activity_ID: 0
A31: OK | B31: activities | C31: no unexpected missing values
A32: INFO | B32: service | C32: 4,251 rows, 9 columns
A33: OK | B33: service | C33: duplicate Service_ID: 0
... A47: INFO | B47: accounts | C47: LEAKAGE GUARD: Churn_Status excluded from churn features; only observable health/contract/spend signals used

Sheet Leads Raw
A1: Lead_ID | B1: Company_Name | C1: Industry | D1: Company_Size | E1: Fleet_Size | F1: Lead_Source | G1: Product_Interest | H1: Units_Requested | I1: Budget_Allocated | J1: Budget_Range | K1: Deal_Value_AED | L1: Sales_Stage | M1: Lead_Created_Date | N1: Last_Contact_Date | O1: Days_in_Pipeline | P1: Number_of_Sales_Calls | Q1: Days_Since_Last_Contact | R1: Emirate | S1: City | T1: Salesperson_ID | U1: Salesperson | V1: Sales_Cycle_Days | W1: Converted_to_Sale | X1: Conversion_Date | Y1: Lost_Reason
A2: L00001 | B2: Gulf Fowler Logistics LLC | C2: Retail Distribution | D2: Large (250-999) | E2: 119 | F2: Email | G2: Heavy Trucks | H2: 45 | I2: No | J2: 4M+ | K2: 15774000 | L2: Lost | M2: 2024-09-07 | N2: 2026-06-28 | O2: 661 | P2: 1 | Q2: 2 | R2: Abu Dhabi | S2: Mussafah | T2: SP-08 | U2: Ahmed Siddiqui | W2: 0 | Y2: Spec Mismatch
A3: L00002 | B3: Emirates Johnson Logistics LLC | C3: Car Rental & Leasing | D3: Medium (50-249) | E3: 20 | F3: Trade Shows | G3: Light Commercial Vans | H3: 5 | I3: Yes | J3: 500K - 1.5M | K3: 503000 | L3: Proposal | M3: 2024-12-06 | N3: 2026-05-08 | O3: 571 | P3: 5 | Q3: 53 | R3: Ras Al Khaimah | S3: RAK Maritime City | T3: SP-08 | U3: Ahmed Siddiqui | W3: 0
A4: L00003 | B4: Al Noor Hill Logistics LLC | C4: Government & Municipal | D4: Enterprise (1000+) | E4: 127 | F4: Partners | G4: Earth-Moving Equipment | H4: 39 | I4: Yes | J4: 4M+ | K4: 19123000 | L4: Won | M4: 2025-01-22 | N4: 2026-06-07 | O4: 524 | P4: 6 | Q4: 23 | R4: Dubai | S4: Al Quoz | T4: SP-05 | U4: Rashid Al Mansoori | V4: 42 | W4: 1 | X4: 2025-03-05
A5: L00004 | B5: Desert Walker Logistics LLC | C5: Facilities Management | D5: Large (250-999) | E5: 59 | F5: Trade Shows | G5: Light Commercial Vans | H5: 27 | I5: Yes | J5: 1.5M - 4M | K5: 2467000 | L5: Lost | M5: 2025-10-06 | N5: 2026-05-30 | O5: 267 | P5: 6 | Q5: 31 | R5: Dubai | S5: Deira | T5: SP-04 | U5: Elena Petrova | W5: 0 | Y5: Spec Mismatch
A6: L00005 | B6: Falcon Doyle Logistics LLC | C6: Logistics & Transport | D6: Small (<50) | E6: 7 | F6: Website | G6: Light Commercial Vans | H6: 2 | I6: Yes | J6: < 500K | K6: 176000 | L6: Negotiation | M6: 2026-04-18 | N6: 2026-06-17 | O6: 73 | P6: 7 | Q6: 13 | R6: Ajman | S6: Al Jurf | T6: SP-08 | U6: Ahmed Siddiqui | W6: 0
A7: L00006 | B7: Arabian Rhodes Logistics LLC | C7: Hospitality & Tourism | D7: Enterprise (1000+) | E7: 216 | F7: LinkedIn | G7: Heavy Trucks | H7: 45 | I7: Yes | J7: 4M+ | K7: 15345000 | L7: Won | M7: 2026-04-09 | N7: 2026-04-23 | O7: 82 | P7: 5 | Q7: 68 | R7: Sharjah | S7: Industrial Area | T7: SP-02 | U7: Priya Nair | V7: 77 | W7: 1 | X7: 2026-06-25
A8: L00007 | B8: Oasis Mcclain Logistics LLC | C8: Retail Distribution | D8: Medium (50-249) | E8: 38 | F8: Website | G8: Passenger Sedan Fleet | H8: 9 | I8: Yes | J8: 500K - 1.5M | K8: 720000 | L8: Negotiation | M8: 2025-11-28 | N8: 2026-05-21 | O8: 214 | P8: 8 | Q8: 40 | R8: Abu Dhabi | S8: Al Ain | T8: SP-02 | U8: Priya Nair | W8: 0
A9: L00008 | B9: Zenith Miller Contracting LLC | C9: Retail Distribution | D9: Small (<50) | E9: 14 | F9: LinkedIn | G9: SUV Fleet | H9: 7 | I9: No | J9: 500K - 1.5M | K9: 1198000 | L9: Won | M9: 2025-12-16 | N9: 2026-03-07 | O9: 196 | P9: 1 | Q9: 115 | R9: Ajman | S9: Ajman Industrial | T9: SP-08 | U9: Ahmed Siddiqui | V9: 50 | W9: 1 | X9: 2026-02-04
A10: L00009 | B10: Horizon Henderson Contracting LLC | C10: Logistics & Transport | D10: Small (<50) | E10: 11 | F10: LinkedIn | G10: SUV Fleet | H10: 4 | I10: Yes | J10: 500K - 1.5M | K10: 736000 | L10: Lost | M10: 2025-04-13 | N10: 2026-05-16 | O10: 443 | P10: 4 | Q10: 45 | R10: Ras Al Khaimah | S10: RAK Maritime City | T10: SP-06 | U10: Daniel Okafor | W10: 0 | Y10: Spec Mismatch
A11: L00010 | B11: Nakheel Johnson Contracting LLC | C11: Car Rental & Leasing | D11: Large (250-999) | E11: 122 | F11: Referral | G11: SUV Fleet | H11: 45 | I11: Yes | J11: 4M+ | K11: 7251000 | L11: Won | M11: 2025-08-25 | N11: 2026-04-14 | O11: 309 | P11: 11 | Q11: 77 | R11: Abu Dhabi | S11: Al Ain | T11: SP-05 | U11: Rashid Al Mansoori | V11: 103 | W11: 1 | X11: 2025-12-06
A12: L00011 | B12: Sahara Robinson Contracting LLC | C12: Construction & Contracting | D12: Small (<50) | E12: 4 | F12: Trade Shows | G12: SUV Fleet | H12: 2 | I12: No | J12: < 500K | K12: 355000 | L12: Lost | M12: 2024-10-26 | N12: 2026-04-16 | O12: 612 | P12: 3 | Q12: 75 | R12: Umm Al Quwain | S12: UAQ Industrial Area | T12: SP-02 | U12: Priya Nair | W12: 0 | Y12: Timing Deferred
A13: L00012 | B13: Crescent Wagner Contracting LLC | C13: Hospitality & Tourism | D13: Small (<50) | E13: 4 | F13: LinkedIn | G13: Passenger Sedan Fleet | H13: 2 | I13: No | J13: < 500K | K13: 160000 | L13: Lost | M13: 2025-06-15 | N13: 2026-05-17 | O13: 380 | P13: 4 | Q13: 44 | R13: Sharjah | S13: Hamriyah Free Zone | T13: SP-05 | U13: Rashid Al Mansoori | W13: 0 | Y13: Competitor Won
A14: L00013 | B14: Pearl Johnson Contracting LLC | C14: Facilities Management | D14: Small (<50) | E14: 13 | F14: Outbound | G14: Light Commercial Vans | H14: 6 | I14: No | J14: 500K - 1.5M | K14: 543000 | L14: Lost | M14: 2025-01-18 | N14: 2026-03-03 | O14: 528 | P14: 4 | Q14: 119 | R14: Sharjah | S14: Industrial Area | T14: SP-08 | U14: Ahmed Siddiqui | W14: 0 | Y14: Competitor Won
A15: L00014 | B15: Cedar Gonzalez Contracting LLC | C15: Retail Distribution | D15: Medium (50-249) | E15: 31 | F15: LinkedIn | G15: Passenger Sedan Fleet | H15: 7 | I15: Yes | J15: < 500K | K15: 498000 | L15: Negotiation | M15: 2026-04-02 | N15: 2026-04-02 | O15: 89 | P15: 5 | Q15: 89 | R15: Abu Dhabi | S15: Al Ain | T15: SP-05 | U15: Rashid Al Mansoori | W15: 0
A16: L00015 | B16: Marina Santos Transport Co | C16: Car Rental & Leasing | D16: Medium (50-249) | E16: 18 | F16: Referral | G16: Light Commercial Vans | H16: 8 | I16: Yes | J16: 500K - 1.5M | K16: 787000 | L16: Won | M16: 2025-03-11 | N16: 2026-04-22 | O16: 476 | P16: 5 | Q16: 69 | R16: Dubai | S16: Al Quoz | T16: SP-04 | U16: Elena Petrova | V16: 61 | W16: 1 | X16: 2025-05-11
A17: L00016 | B17: Summit Gardner Transport Co | C17: Construction & Contracting | D17: Medium (50-249) | E17: 37 | F17: Website | G17: Light Commercial Vans | H17: 18 | I17: Yes | J17: 1.5M - 4M | K17: 1651000 | L17: Lost | M17: 2025-03-30 | N17: 2026-04-18 | O17: 457 | P17: 4 | Q17: 73 | R17: Dubai | S17: Al Quoz | T17: SP-05 | U17: Rashid Al Mansoori | W17: 0 | Y17: Competitor Won
A18: L00017 | B18: Delta Robinson Transport Co | C18: Oil & Gas Services | D18: Small (<50) | E18: 5 | F18: Trade Shows | G18: Light Commercial Vans | H18: 2 | I18: Yes | J18: < 500K | K18: 200000 | L18: Won | M18: 2025-04-04 | N18: 2026-03-12 | O18: 452 | P18: 4 | Q18: 110 | R18: Ajman | S18: Al Jurf | T18: SP-08 | U18: Ahmed Siddiqui | V18: 74 | W18: 1 | X18: 2025-06-17
A19: L00018 | B19: Vertex Lawrence Transport Co | C19: Logistics & Transport | D19: Small (<50) | E19: 12 | F19: Website | G19: SUV Fleet | H19: 2 | I19: Yes | J19: < 500K | K19: 348000 | L19: Qualified | M19: 2026-03-14 | N19: 2026-03-14 | O19: 108 | P19: 4 | Q19: 108 | R19: Sharjah | S19: Industrial Area | T19: SP-08 | U19: Ahmed Siddiqui | W19: 0
A20: L00019 | B20: Anchor Pacheco Transport Co | C20: Retail Distribution | D20: Medium (50-249) | E20: 40 | F20: LinkedIn | G20: Passenger Sedan Fleet | H20: 13 | I20: Yes | J20: 500K - 1.5M | K20: 1014000 | L20: Won | M20: 2026-04-05 | N20: 2026-04-05 | O20: 86 | P20: 6 | Q20: 86 | R20: Dubai | S20: Dubai Investment Park | T20: SP-04 | U20: Elena Petrova | V20: 48 | W20: 1 | X20: 2026-05-23
A21: L00020 | B21: Meridian Smith Transport Co | C21: Facilities Management | D21: Medium (50-249) | E21: 27 | F21: Email | G21: Bus Fleet | H21: 6 | I21: No | J21: 500K - 1.5M | K21: 1466000 | L21: Lost | M21: 2025-04-24 | N21: 2026-06-14 | O21: 432 | P21: 1 | Q21: 16 | R21: Sharjah | S21: Hamriyah Free Zone | T21: SP-05 | U21: Rashid Al Mansoori | W21: 0 | Y21: Spec Mismatch
A22: L00021 | B22: Gulf Shaffer Transport Co | C22: Retail Distribution | D22: Large (250-999) | E22: 102 | F22: LinkedIn | G22: Bus Fleet | H22: 45 | I22: Yes | J22: 4M+ | K22: 11209000 | L22: Won | M22: 2026-05-19 | N22: 2026-06-08 | O22: 42 | P22: 5 | Q22: 22 | R22: Dubai | S22: Al Quoz | T22: SP-03 | U22: Hassan Khoury | V22: 37 | W22: 1 | X22: 2026-06-25
A23: L00022 | B23: Emirates Wolfe Rentals LLC | C23: Construction & Contracting | D23: Small (<50) | E23: 11 | F23: LinkedIn | G23: SUV Fleet | H23: 3 | I23: Yes | J23: < 500K | K23: 497000 | L23: Lost | M23: 2025-12-05 | N23: 2026-05-02 | O23: 207 | P23: 2 | Q23: 59 | R23: Dubai | S23: Jebel Ali | T23: SP-04 | U23: Elena Petrova | W23: 0 | Y23: No Decision / Stalled
A24: L00023 | B24: Al Noor Peterson Rentals LLC | C24: Hospitality & Tourism | D24: Small (<50) | E24: 13 | F24: Trade Shows | G24: Light Commercial Vans | H24: 7 | I24: No | J24: 500K - 1.5M | K24: 727000 | L24: Lost | M24: 2026-02-05 | N24: 2026-04-08 | O24: 145 | P24: 3 | Q24: 83 | R24: Fujairah | S24: Dibba | T24: SP-02 | U24: Priya Nair | W24: 0 | Y24: Price / Budget
A25: L00024 | B25: Desert Moore Rentals LLC | C25: Government & Municipal | D25: Small (<50) | E25: 10 | F25: Outbound | G25: SUV Fleet | H25: 5 | I25: Yes | J25: 500K - 1.5M | K25: 756000 | L25: Prospect | M25: 2026-03-24 | N25: 2026-05-13 | O25: 98 | P25: 5 | Q25: 48 | R25: Abu Dhabi | S25: Mussafah | T25: SP-05 | U25: Rashid Al Mansoori | W25: 0
A26: L00025 | B26: Falcon Bernard Rentals LLC | C26: Retail Distribution | D26: Medium (50-249) | E26: 20 | F26: Email | G26: SUV Fleet | H26: 10 | I26: No | J26: 1.5M - 4M | K26: 1841000 | L26: Lost | M26: 2025-02-15 | N26: 2026-03-11 | O26: 500 | P26: 7 | Q26: 111 | R26: Dubai | S26: Jebel Ali | T26: SP-05 | U26: Rashid Al Mansoori | W26: 0 | Y26: No Decision / Stalled
A27: L00026 | B27: Arabian Rogers Rentals LLC | C27: Logistics & Transport | D27: Medium (50-249) | E27: 17 | F27: Outbound | G27: SUV Fleet | H27: 7 | I27: Yes | J27: 500K - 1.5M | K27: 1048000 | L27: Won | M27: 2025-07-15 | N27: 2026-05-23 | O27: 350 | P27: 6 | Q27: 38 | R27: Abu Dhabi | S27: Mussafah | T27: SP-03 | U27: Hassan Khoury | V27: 59 | W27: 1 | X27: 2025-09-12
A28: L00027 | B28: Oasis Davis Rentals LLC | C28: Car Rental & Leasing | D28: Large (250-999) | E28: 69 | F28: Referral | G28: Light Commercial Vans | H28: 18 | I28: Yes | J28: 1.5M - 4M | K28: 1617000 | L28: Negotiation | M28: 2025-01-13 | N28: 2026-04-10 | O28: 533 | P28: 2 | Q28: 81 | R28: Abu Dhabi | S28: Mussafah | T28: SP-03 | U28: Hassan Khoury | W28: 0
A29: L00028 | B29: Zenith Davis Rentals LLC | C29: Logistics & Transport | D29: Medium (50-249) | E29: 11 | F29: Email | G29: Light Commercial Vans | H29: 5 | I29: Yes | J29: 500K - 1.5M | K29: 502000 | L29: Lost | M29: 2025-01-30 | N29: 2026-03-23 | O29: 516 | P29: 4 | Q29: 99 | R29: Sharjah | S29: Industrial Area | T29: SP-02 | U29: Priya Nair | W29: 0 | Y29: Competitor Won
A30: L00029 | B30: Horizon Abbott Industries LLC | C30: Logistics & Transport | D30: Medium (50-249) | E30: 34 | F30: Website | G30: Bus Fleet | H30: 15 | I30: Yes | J30: 1.5M - 4M | K30: 3307000 | L30: Won | M30: 2025-05-17 | N30: 2026-05-18 | O30: 409 | P30: 6 | Q30: 43 | R30: Umm Al Quwain | S30: UAQ Industrial Area | T30: SP-02 | U30: Priya Nair | V30: 22 | W30: 1 | X30: 2025-06-08
A31: L00030 | B31: Nakheel Munoz Industries LLC | C31: Facilities Management | D31: Medium (50-249) | E31: 22 | F31: Outbound | G31: Light Commercial Vans | H31: 12 | I31: No | J31: 500K - 1.5M | K31: 1092000 | L31: Lost | M31: 2024-08-05 | N31: 2026-04-08 | O31: 694 | P31: 2 | Q31: 83 | R31: Sharjah | S31: Industrial Area | T31: SP-06 | U31: Daniel Okafor | W31: 0 | Y31: Price / Budget
A32: L00031 | B32: Sahara Roman Industries LLC | C32: Retail Distribution | D32: Small (<50) | E32: 11 | F32: Website | G32: Pickup Fleet | H32: 3 | I32: Yes | J32: < 500K | K32: 336000 | L32: Lost | M32: 2024-11-26 | N32: 2026-03-27 | O32: 581 | P32: 7 | Q32: 95 | R32: Sharjah | S32: Hamriyah Free Zone | T32: SP-02 | U32: Priya Nair | W32: 0 | Y32: No Decision / Stalled
A33: L00032 | B33: Crescent Blair Industries LLC | C33: Hospitality & Tourism | D33: Medium (50-249) | E33: 12 | F33: Trade Shows | G33: Heavy Trucks | H33: 2 | I33: Yes | J33: 500K - 1.5M | K33: 678000 | L33: Lost | M33: 2026-01-10 | N33: 2026-05-08 | O33: 171 | P33: 3 | Q33: 53 | R33: Abu Dhabi | S33: Ruwais | T33: SP-01 | U33: Omar Al Farsi | W33: 0 | Y33: Timing Deferred
A34: L00033 | B34: Pearl Herrera Industries LLC | C34: Construction & Contracting | D34: Medium (50-249) | E34: 21 | F34: Referral | G34: Light Commercial Vans | H34: 12 | I34: Yes | J34: 500K - 1.5M | K34: 1171000 | L34: Proposal | M34: 2024-10-23 | N34: 2026-02-10 | O34: 615 | P34: 5 | Q34: 140 | R34: Abu Dhabi | S34: Ruwais | T34: SP-08 | U34: Ahmed Siddiqui | W34: 0
A35: L00034 | B35: Cedar Dudley Industries LLC | C35: Construction & Contracting | D35: Medium (50-249) | E35: 23 | F35: Website | G35: Light Commercial Vans | H35: 11 | I35: Yes | J35: 500K - 1.5M | K35: 955000 | L35: Lost | M35: 2025-09-03 | N35: 2026-04-26 | O35: 300 | P35: 7 | Q35: 65 | R35: Dubai | S35: Dubai Investment Park | T35: SP-03 | U35: Hassan Khoury | W35: 0 | Y35: No Decision / Stalled
A36: L00035 | B36: Marina Gray Industries LLC | C36: Car Rental & Leasing | D36: Small (<50) | E36: 4 | F36: LinkedIn | G36: Bus Fleet | H36: 2 | I36: Yes | J36: < 500K | K36: 481000 | L36: Lost | M36: 2025-12-11 | N36: 2026-03-02 | O36: 201 | P36: 2 | Q36: 120 | R36: Dubai | S36: Dubai South | T36: SP-08 | U36: Ahmed Siddiqui | W36: 0 | Y36: No Decision / Stalled
A37: L00036 | B37: Summit Arnold Group | C37: Logistics & Transport | D37: Large (250-999) | E37: 121 | F37: Website | G37: SUV Fleet | H37: 45 | I37: Yes | J37: 4M+ | K37: 7023000 | L37: Lost | M37: 2024-12-29 | N37: 2026-03-28 | O37: 548 | P37: 6 | Q37: 94 | R37: Ras Al Khaimah | S37: RAK Maritime City | T37: SP-05 | U37: Rashid Al Mansoori | W37: 0 | Y37: Competitor Won
A38: L00037 | B38: Delta Calderon Group | C38: Logistics & Transport | D38: Enterprise (1000+) | E38: 275 | F38: Trade Shows | G38: SUV Fleet | H38: 41 | I38: Yes | J38: 4M+ | K38: 7529000 | L38: Won | M38: 2025-05-13 | N38: 2026-03-10 | O38: 413 | P38: 6 | Q38: 112 | R38: Abu Dhabi | S38: Khalifa Industrial Zone | T38: SP-06 | U38: Daniel Okafor | V38: 116 | W38: 1 | X38: 2025-09-06
A39: L00038 | B39: Vertex Montgomery Group | C39: Car Rental & Leasing | D39: Small (<50) | E39: 13 | F39: Partners | G39: Pickup Fleet | H39: 5 | I39: Yes | J39: 500K - 1.5M | K39: 554000 | L39: Won | M39: 2026-02-26 | N39: 2026-03-26 | O39: 124 | P39: 4 | Q39: 96 | R39: Abu Dhabi | S39: Ruwais | T39: SP-05 | U39: Rashid Al Mansoori | V39: 31 | W39: 1 | X39: 2026-03-29
A40: L00039 | B40: Anchor Hensley Group | C40: Construction & Contracting | D40: Medium (50-249) | E40: 38 | F40: Website | G40: Pickup Fleet | H40: 11 | I40: No | J40: 500K - 1.5M | K40: 1362000 | L40: Negotiation | M40: 2026-01-28 | N40: 2026-04-14 | O40: 153 | P40: 3 | Q40: 77 | R40: Dubai | S40: Jebel Ali | T40: SP-02 | U40: Priya Nair | W40: 0
A41: L00040 | B41: Meridian Ray Group | C41: Facilities Management | D41: Large (250-999) | E41: 33 | F41: Partners | G41: Heavy Trucks | H41: 10 | I41: Yes | J41: 1.5M - 4M | K41: 3219000 | L41: Won | M41: 2026-03-28 | N41: 2026-03-28 | O41: 94 | P41: 5 | Q41: 94 | R41: Ras Al Khaimah | S41: Al Ghail | T41: SP-07 | U41: Mei Lin Tan | V41: 62 | W41: 1 | X41: 2026-05-29
A42: L00041 | B42: Gulf Bush Group | C42: Car Rental & Leasing | D42: Small (<50) | E42: 13 | F42: Website | G42: Heavy Trucks | H42: 3 | I42: No | J42: 500K - 1.5M | K42: 986000 | L42: Lost | M42: 2025-09-07 | N42: 2026-04-22 | O42: 296 | P42: 2 | Q42: 69 | R42: Dubai | S42: Jebel Ali | T42: SP-07 | U42: Mei Lin Tan | W42: 0 | Y42: Timing Deferred
A43: L00042 | B43: Emirates Williams Group | C43: Retail Distribution | D43: Large (250-999) | E43: 37 | F43: Email | G43: Light Commercial Vans | H43: 10 | I43: Yes | J43: 500K - 1.5M | K43: 1055000 | L43: Proposal | M43: 2026-03-05 | N43: 2026-03-05 | O43: 117 | P43: 6 | Q43: 117 | R43: Abu Dhabi | S43: Khalifa Industrial Zone | T43: SP-03 | U43: Hassan Khoury | W43: 0
A44: L00043 | B44: Al Noor Perez Trading LLC | C44: Facilities Management | D44: Medium (50-249) | E44: 40 | F44: LinkedIn | G44: SUV Fleet | H44: 13 | I44: Yes | J44: 1.5M - 4M | K44: 2092000 | L44: Won | M44: 2025-04-01 | N44: 2026-04-29 | O44: 455 | P44: 6 | Q44: 62 | R44: Ras Al Khaimah | S44: RAK Maritime City | T44: SP-07 | U44: Mei Lin Tan | V44: 42 | W44: 1 | X44: 2025-05-13
A45: L00044 | B45: Desert Roberts Trading LLC | C45: Construction & Contracting | D45: Enterprise (1000+) | E45: 297 | F45: Outbound | G45: Bus Fleet | H45: 45 | I45: No | J45: 4M+ | K45: 11499000 | L45: Lost | M45: 2025-08-20 | N45: 2026-03-16 | O45: 314 | P45: 4 | Q45: 106 | R45: Abu Dhabi | S45: Mussafah | T45: SP-05 | U45: Rashid Al Mansoori | W45: 0 | Y45: Spec Mismatch
A46: L00045 | B46: Falcon Miller Trading LLC | C46: Retail Distribution | D46: Enterprise (1000+) | E46: 344 | F46: Website | G46: Earth-Moving Equipment | H46: 45 | I46: Yes | J46: 4M+ | K46: 21117000 | L46: Won | M46: 2025-10-04 | N46: 2026-05-28 | O46: 269 | P46: 0 | Q46: 33 | R46: Fujairah | S46: Dibba | T46: SP-08 | U46: Ahmed Siddiqui | V46: 83 | W46: 1 | X46: 2025-12-26
A47: L00046 | B47: Arabian Hall Trading LLC | C47: Retail Distribution | D47: Small (<50) | E47: 8 | F47: Trade Shows | G47: Heavy Trucks | H47: 3 | I47: Yes | J47: 500K - 1.5M | K47: 1004000 | L47: Won | M47: 2026-05-05 | N47: 2026-06-22 | O47: 56 | P47: 7 | Q47: 8 | R47: Dubai | S47: Al Quoz | T47: SP-07 | U47: Mei Lin Tan | V47: 56 | W47: 1 | X47: 2026-06-30
A48: L00047 | B48: Oasis Garcia Trading LLC | C48: Car Rental & Leasing | D48: Medium (50-249) | E48: 15 | F48: Trade Shows | G48: Heavy Trucks | H48: 7 | I48: No | J48: 1.5M - 4M | K48: 2196000 | L48: Lost | M48: 2025-03-12 | N48: 2026-04-07 | O48: 475 | P48: 2 | Q48: 84 | R48: Sharjah | S48: Al Sajaa | T48: SP-01 | U48: Omar Al Farsi | W48: 0 | Y48: Timing Deferred
A49: L00048 | B49: Zenith Ramirez Trading LLC | C49: Construction & Contracting | D49: Medium (50-249) | E49: 15 | F49: Trade Shows | G49: Light Commercial Vans | H49: 6 | I49: No | J49: 500K - 1.5M | K49: 541000 | L49: Lost | M49: 2026-02-24 | N49: 2026-02-24 | O49: 126 | P49: 0 | Q49: 126 | R49: Umm Al Quwain | S49: UAQ Industrial Area | T49: SP-08 | U49: Ahmed Siddiqui | W49: 0 | Y49: Competitor Won
A50: L00049 | B50: Horizon Reid Trading LLC | C50: Facilities Management | D50: Small (<50) | E50: 4 | F50: Website | G50: Pickup Fleet | H50: 2 | I50: Yes | J50: < 500K | K50: 220000 | L50: Lost | M50: 2025-06-17 | N50: 2026-03-20 | O50: 378 | P50: 5 | Q50: 102 | R50: Abu Dhabi | S50: Al Ain | T50: SP-08 | U50: Ahmed Siddiqui | W50: 0 | Y50: Competitor Won
A51: L00050 | B51: Nakheel Diaz Services FZE | C51: Logistics & Transport | D51: Medium (50-249) | E51: 38 | F51: Email | G51: Heavy Trucks | H51: 6 | I51: Yes | J51: 1.5M - 4M | K51: 1771000 | L51: Won | M51: 2024-09-10 | N51: 2026-05-14 | O51: 658 | P51: 2 | Q51: 47 | R51: Sharjah | S51: Industrial Area | T51: SP-06 | U51: Daniel Okafor | V51: 55 | W51: 1 | X51: 2024-11-04
A52: L00051 | B52: Sahara Wood Services FZE | C52: Logistics & Transport | D52: Enterprise (1000+) | E52: 255 | F52: Outbound | G52: Heavy Trucks | H52: 45 | I52: No | J52: 4M+ | K52: 15999000 | L52: Won | M52: 2025-09-26 | N52: 2026-02-25 | O52: 277 | P52: 4 | Q52: 125 | R52: Abu Dhabi | S52: Ruwais | T52: SP-01 | U52: Omar Al Farsi | V52: 97 | W52: 1 | X52: 2026-01-01
A53: L00052 | B53: Crescent Clark Services FZE | C53: Logistics & Transport | D53: Small (<50) | E53: 5 | F53: Email | G53: Earth-Moving Equipment | H53: 2 | I53: No | J53: 500K - 1.5M | K53: 1009000 | L53: Prospect | M53: 2026-05-08 | N53: 2026-05-08 | O53: 53 | P53: 0 | Q53: 53 | R53: Ajman | S53: Al Jurf | T53: SP-07 | U53: Mei Lin Tan | W53: 0
A54: L00053 | B54: Pearl Adams Services FZE | C54: Retail Distribution | D54: Medium (50-249) | E54: 14 | F54: Website | G54: SUV Fleet | H54: 8 | I54: Yes | J54: 500K - 1.5M | K54: 1259000 | L54: Proposal | M54: 2025-05-09 | N54: 2026-04-08 | O54: 417 | P54: 2 | Q54: 83 | R54: Ras Al Khaimah | S54: Al Ghail | T54: SP-06 | U54: Daniel Okafor | W54: 0
A55: L00054 | B55: Cedar Zuniga Services FZE | C55: Facilities Management | D55: Large (250-999) | E55: 38 | F55: Website | G55: Pickup Fleet | H55: 20 | I55: Yes | J55: 1.5M - 4M | K55: 2439000 | L55: Negotiation | M55: 2025-07-14 | N55: 2026-02-10 | O55: 351 | P55: 6 | Q55: 140 | R55: Sharjah | S55: Industrial Area | T55: SP-03 | U55: Hassan Khoury | W55: 0
A56: L00055 | B56: Marina Wong Services FZE | C56: Facilities Management | D56: Medium (50-249) | E56: 19 | F56: Partners | G56: Light Commercial Vans | H56: 8 | I56: Yes | J56: 500K - 1.5M | K56: 803000 | L56: Won | M56: 2026-04-01 | N56: 2026-04-01 | O56: 90 | P56: 3 | Q56: 90 | R56: Fujairah | S56: Fujairah Free Zone | T56: SP-08 | U56: Ahmed Siddiqui | V56: 51 | W56: 1 | X56: 2026-05-22
A57: L00056 | B57: Summit Lynch Services FZE | C57: Retail Distribution | D57: Medium (50-249) | E57: 36 | F57: Partners | G57: Light Commercial Vans | H57: 18 | I57: Yes | J57: 1.5M - 4M | K57: 1672000 | L57: Lost | M57: 2026-03-27 | N57: 2026-06-04 | O57: 95 | P57: 7 | Q57: 26 | R57: Abu Dhabi | S57: Mussafah | T57: SP-05 | U57: Rashid Al Mansoori | W57: 0 | Y57: Price / Budget
A58: L00057 | B58: Delta Jackson Holdings | C58: Car Rental & Leasing | D58: Enterprise (1000+) | E58: 366 | F58: Trade Shows | G58: Light Commercial Vans | H58: 45 | I58: Yes | J58: 4M+ | K58: 4261000 | L58: Proposal | M58: 2025-04-03 | N58: 2026-06-29 | O58: 453 | P58: 5 | Q58: 1 | R58: Abu Dhabi | S58: Ruwais | T58: SP-07 | U58: Mei Lin Tan | W58: 0
A59: L00058 | B59: Vertex Daniel Holdings | C59: Oil & Gas Services | D59: Medium (50-249) | E59: 31 | F59: Outbound | G59: Earth-Moving Equipment | H59: 14 | I59: No | J59: 4M+ | K59: 6962000 | L59: Lost | M59: 2025-12-07 | N59: 2026-05-24 | O59: 205 | P59: 2 | Q59: 37 | R59: Dubai | S59: Dubai Investment Park | T59: SP-06 | U59: Daniel Okafor | W59: 0 | Y59: Timing Deferred
A60: L00059 | B60: Anchor Martin Holdings | C60: Logistics & Transport | D60: Small (<50) | E60: 14 | F60: Website | G60: SUV Fleet | H60: 7 | I60: No | J60: 500K - 1.5M | K60: 1097000 | L60: Proposal | M60: 2025-09-09 | N60: 2026-06-07 | O60: 294 | P60: 2 | Q60: 23 | R60: Sharjah | S60: Industrial Area | T60: SP-03 | U60: Hassan Khoury | W60: 0
A61: L00060 | B61: Meridian Gray Holdings | C61: Logistics & Transport | D61: Small (<50) | E61: 7 | F61: Partners | G61: SUV Fleet | H61: 3 | I61: Yes | J61: 500K - 1.5M | K61: 503000 | L61: Lost | M61: 2025-09-20 | N61: 2026-06-10 | O61: 283 | P61: 3 | Q61: 20 | R61: Ras Al Khaimah | S61: RAK Maritime City | T61: SP-08 | U61: Ahmed Siddiqui | W61: 0 | Y61: Spec Mismatch
A62: L00061 | B62: Gulf Mayo Holdings | C62: Facilities Management | D62: Enterprise (1000+) | E62: 193 | F62: Outbound | G62: Passenger Sedan Fleet | H62: 45 | I62: Yes | J62: 1.5M - 4M | K62: 3321000 | L62: Lost | M62: 2025-11-10 | N62: 2026-05-04 | O62: 232 | P62: 9 | Q62: 57 | R62: Sharjah | S62: Al Sajaa | T62: SP-05 | U62: Rashid Al Mansoori | W62: 0 | Y62: Spec Mismatch
A63: L00062 | B63: Emirates Bowman Holdings | C63: Car Rental & Leasing | D63: Small (<50) | E63: 11 | F63: Email | G63: Heavy Trucks | H63: 3 | I63: No | J63: 500K - 1.5M | K63: 865000 | L63: Lost | M63: 2025-02-11 | N63: 2026-02-02 | O63: 504 | P63: 3 | Q63: 148 | R63: Dubai | S63: Al Quoz | T63: SP-05 | U63: Rashid Al Mansoori | W63: 0 | Y63: Price / Budget
A64: L00063 | B64: Al Noor Hawkins Holdings | C64: Oil & Gas Services | D64: Medium (50-249) | E64: 14 | F64: LinkedIn | G64: Light Commercial Vans | H64: 4 | I64: Yes | J64: < 500K | K64: 400000 | L64: Lost | M64: 2025-01-27 | N64: 2026-03-30 | O64: 519 | P64: 4 | Q64: 92 | R64: Abu Dhabi | S64: Khalifa Industrial Zone | T64: SP-04 | U64: Elena Petrova | W64: 0 | Y64: Competitor Won
A65: L00064 | B65: Desert Cohen Equipment LLC | C65: Retail Distribution | D65: Small (<50) | E65: 13 | F65: Referral | G65: Heavy Trucks | H65: 4 | I65: Yes | J65: 500K - 1.5M | K65: 1351000 | L65: Won | M65: 2024-07-19 | N65: 2026-05-11 | O65: 711 | P65: 6 | Q65: 50 | R65: Ajman | S65: Al Jurf | T65: SP-02 | U65: Priya Nair | V65: 18 | W65: 1 | X65: 2024-08-06
A66: L00065 | B66: Falcon Cameron Equipment LLC | C66: Facilities Management | D66: Medium (50-249) | E66: 37 | F66: LinkedIn | G66: Pickup Fleet | H66: 18 | I66: Yes | J66: 1.5M - 4M | K66: 2417000 | L66: Won | M66: 2026-02-11 | N66: 2026-05-30 | O66: 139 | P66: 3 | Q66: 31 | R66: Fujairah | S66: Dibba | T66: SP-06 | U66: Daniel Okafor | V66: 59 | W66: 1 | X66: 2026-04-11
A67: L00066 | B67: Arabian Parsons Equipment LLC | C67: Oil & Gas Services | D67: Enterprise (1000+) | E67: 100 | F67: Email | G67: SUV Fleet | H67: 43 | I67: No | J67: 4M+ | K67: 6668000 | L67: Negotiation | M67: 2025-01-07 | N67: 2026-03-06 | O67: 539 | P67: 3 | Q67: 116 | R67: Dubai | S67: Al Quoz | T67: SP-04 | U67: Elena Petrova | W67: 0
A68: L00067 | B68: Oasis Perez Equipment LLC | C68: Oil & Gas Services | D68: Medium (50-249) | E68: 16 | F68: Trade Shows | G68: Heavy Trucks | H68: 4 | I68: Yes | J68: 500K - 1.5M | K68: 1360000 | L68: Lost | M68: 2025-10-09 | N68: 2026-04-21 | O68: 264 | P68: 6 | Q68: 70 | R68: Dubai | S68: Deira | T68: SP-08 | U68: Ahmed Siddiqui | W68: 0 | Y68: Price / Budget
A69: L00068 | B69: Zenith Johnson Equipment LLC | C69: Construction & Contracting | D69: Enterprise (1000+) | E69: 284 | F69: Email | G69: Pickup Fleet | H69: 45 | I69: Yes | J69: 4M+ | K69: 5986000 | L69: Won | M69: 2025-10-17 | N69: 2026-06-29 | O69: 256 | P69: 7 | Q69: 1 | R69: Abu Dhabi | S69: Ruwais | T69: SP-08 | U69: Ahmed Siddiqui | V69: 90 | W69: 1 | X69: 2026-01-15
A70: L00069 | B70: Horizon Stewart Equipment LLC | C70: Logistics & Transport | D70: Small (<50) | E70: 11 | F70: Outbound | G70: Pickup Fleet | H70: 3 | I70: No | J70: < 500K | K70: 375000 | L70: Negotiation | M70: 2025-10-29 | N70: 2026-04-22 | O70: 244 | P70: 2 | Q70: 69 | R70: Dubai | S70: Deira | T70: SP-07 | U70: Mei Lin Tan | W70: 0
A71: L00070 | B71: Nakheel Adams Equipment LLC | C71: Car Rental & Leasing | D71: Medium (50-249) | E71: 17 | F71: LinkedIn | G71: Light Commercial Vans | H71: 6 | I71: No | J71: 500K - 1.5M | K71: 634000 | L71: Prospect | M71: 2026-02-16 | N71: 2026-06-13 | O71: 134 | P71: 4 | Q71: 17 | R71: Umm Al Quwain | S71: UAQ Industrial Area | T71: SP-02 | U71: Priya Nair | W71: 0
A72: L00071 | B72: Sahara Clark Freight LLC | C72: Construction & Contracting | D72: Large (250-999) | E72: 112 | F72: Website | G72: SUV Fleet | H72: 33 | I72: Yes | J72: 4M+ | K72: 6092000 | L72: Negotiation | M72: 2026-02-19 | N72: 2026-05-02 | O72: 131 | P72: 7 | Q72: 59 | R72: Abu Dhabi | S72: Ruwais | T72: SP-06 | U72: Daniel Okafor | W72: 0
A73: L00072 | B73: Crescent Hahn Freight LLC | C73: Car Rental & Leasing | D73: Medium (50-249) | E73: 26 | F73: Referral | G73: Light Commercial Vans | H73: 9 | I73: Yes | J73: 500K - 1.5M | K73: 920000 | L73: Won | M73: 2024-07-02 | N73: 2026-06-29 | O73: 728 | P73: 11 | Q73: 1 | R73: Abu Dhabi | S73: Mussafah | T73: SP-01 | U73: Omar Al Farsi | V73: 63 | W73: 1 | X73: 2024-09-03
A74: L00073 | B74: Pearl Walter Freight LLC | C74: Government & Municipal | D74: Small (<50) | E74: 11 | F74: Website | G74: Light Commercial Vans | H74: 5 | I74: Yes | J74: 500K - 1.5M | K74: 532000 | L74: Prospect | M74: 2026-01-31 | N74: 2026-06-14 | O74: 150 | P74: 6 | Q74: 16 | R74: Dubai | S74: Deira | T74: SP-07 | U74: Mei Lin Tan | W74: 0
A75: L00074 | B75: Cedar Edwards Freight LLC | C75: Construction & Contracting | D75: Large (250-999) | E75: 76 | F75: LinkedIn | G75: Light Commercial Vans | H75: 34 | I75: Yes | J75: 1.5M - 4M | K75: 3352000 | L75: Lost | M75: 2024-11-21 | N75: 2026-03-04 | O75: 586 | P75: 4 | Q75: 118 | R75: Abu Dhabi | S75: Ruwais | T75: SP-04 | U75: Elena Petrova | W75: 0 | Y75: Spec Mismatch
A76: L00075 | B76: Marina Rios Freight LLC | C76: Logistics & Transport | D76: Medium (50-249) | E76: 25 | F76: LinkedIn | G76: SUV Fleet | H76: 11 | I76: No | J76: 1.5M - 4M | K76: 1832000 | L76: Lost | M76: 2025-09-19 | N76: 2026-06-09 | O76: 284 | P76: 2 | Q76: 21 | R76: Umm Al Quwain | S76: UAQ Industrial Area | T76: SP-08 | U76: Ahmed Siddiqui | W76: 0 | Y76: Price / Budget
A77: L00076 | B77: Summit Foster Freight LLC | C77: Construction & Contracting | D77: Medium (50-249) | E77: 23 | F77: Website | G77: Earth-Moving Equipment | H77: 7 | I77: No | J77: 1.5M - 4M | K77: 3625000 | L77: Proposal | M77: 2025-10-08 | N77: 2026-06-13 | O77: 265 | P77: 0 | Q77: 17 | R77: Abu Dhabi | S77: Khalifa Industrial Zone | T77: SP-04 | U77: Elena Petrova | W77: 0
A78: L00077 | B78: Delta Rocha Freight LLC | C78: Construction & Contracting | D78: Enterprise (1000+) | E78: 138 | F78: Referral | G78: Passenger Sedan Fleet | H78: 45 | I78: Yes | J78: 1.5M - 4M | K78: 3801000 | L78: Won | M78: 2024-08-07 | N78: 2026-06-18 | O78: 692 | P78: 8 | Q78: 12 | R78: Dubai | S78: Dubai South | T78: SP-03 | U78: Hassan Khoury | V78: 50 | W78: 1 | X78: 2024-09-26
A79: L00078 | B79: Vertex Ellis Facilities LLC | C79: Facilities Management | D79: Small (<50) | E79: 5 | F79: Referral | G79: Pickup Fleet | H79: 2 | I79: Yes | J79: < 500K | K79: 222000 | L79: Won | M79: 2025-01-12 | N79: 2026-02-18 | O79: 534 | P79: 5 | Q79: 132 | R79: Dubai | S79: Al Quoz | T79: SP-08 | U79: Ahmed Siddiqui | V79: 48 | W79: 1 | X79: 2025-03-01
A80: L00079 | B80: Anchor Baker Facilities LLC | C80: Oil & Gas Services | D80: Medium (50-249) | E80: 15 | F80: LinkedIn | G80: Light Commercial Vans | H80: 5 | I80: No | J80: < 500K | K80: 459000 | L80: Prospect | M80: 2026-03-20 | N80: 2026-03-20 | O80: 102 | P80: 3 | Q80: 102 | R80: Umm Al Quwain | S80: UAQ Industrial Area | T80: SP-05 | U80: Rashid Al Mansoori | W80: 0
A81: L00080 | B81: Meridian Wright Facilities LLC | C81: Retail Distribution | D81: Small (<50) | E81: 12 | F81: Website | G81: SUV Fleet | H81: 5 | I81: No | J81: 500K - 1.5M | K81: 790000 | L81: Lost | M81: 2024-10-06 | N81: 2026-03-25 | O81: 632 | P81: 3 | Q81: 97 | R81: Umm Al Quwain | S81: UAQ Industrial Area | T81: SP-07 | U81: Mei Lin Tan | W81: 0 | Y81: Competitor Won
A82: L00081 | B82: Gulf Hoffman Facilities LLC | C82: Facilities Management | D82: Medium (50-249) | E82: 24 | F82: Website | G82: Light Commercial Vans | H82: 10 | I82: No | J82: 500K - 1.5M | K82: 1034000 | L82: Lost | M82: 2024-12-07 | N82: 2026-02-28 | O82: 570 | P82: 1 | Q82: 122 | R82: Dubai | S82: Dubai South | T82: SP-08 | U82: Ahmed Siddiqui | W82: 0 | Y82: Price / Budget
A83: L00082 | B83: Emirates Baker Facilities LLC | C83: Car Rental & Leasing | D83: Small (<50) | E83: 7 | F83: Trade Shows | G83: Light Commercial Vans | H83: 4 | I83: Yes | J83: < 500K | K83: 361000 | L83: Won | M83: 2024-08-26 | N83: 2026-02-20 | O83: 673 | P83: 5 | Q83: 130 | R83: Sharjah | S83: Al Sajaa | T83: SP-05 | U83: Rashid Al Mansoori | V83: 55 | W83: 1 | X83: 2024-10-20
A84: L00083 | B84: Al Noor Richards Facilities LLC | C84: Retail Distribution | D84: Large (250-999) | E84: 124 | F84: Email | G84: Earth-Moving Equipment | H84: 34 | I84: Yes | J84: 4M+ | K84: 15451000 | L84: Lost | M84: 2024-10-24 | N84: 2026-05-25 | O84: 614 | P84: 4 | Q84: 36 | R84: Dubai | S84: Deira | T84: SP-04 | U84: Elena Petrova | W84: 0 | Y84: Timing Deferred
A85: L00084 | B85: Desert Hurst Facilities LLC | C85: Logistics & Transport | D85: Small (<50) | E85: 13 | F85: Trade Shows | G85: Light Commercial Vans | H85: 6 | I85: Yes | J85: 500K - 1.5M | K85: 578000 | L85: Won | M85: 2025-09-14 | N85: 2026-05-04 | O85: 289 | P85: 3 | Q85: 57 | R85: Abu Dhabi | S85: Khalifa Industrial Zone | T85: SP-05 | U85: Rashid Al Mansoori | V85: 69 | W85: 1 | X85: 2025-11-22
A86: L00085 | B86: Falcon Ross Motors LLC | C86: Logistics & Transport | D86: Large (250-999) | E86: 55 | F86: Website | G86: Light Commercial Vans | H86: 15 | I86: No | J86: 500K - 1.5M | K86: 1306000 | L86: Lost | M86: 2026-02-01 | N86: 2026-06-29 | O86: 149 | P86: 4 | Q86: 1 | R86: Dubai | S86: Jebel Ali | T86: SP-07 | U86: Mei Lin Tan | W86: 0 | Y86: Spec Mismatch
A87: L00086 | B87: Arabian Robinson Motors LLC | C87: Logistics & Transport | D87: Small (<50) | E87: 7 | F87: Outbound | G87: SUV Fleet | H87: 3 | I87: No | J87: 500K - 1.5M | K87: 550000 | L87: Lost | M87: 2025-08-15 | N87: 2026-04-07 | O87: 319 | P87: 0 | Q87: 84 | R87: Ajman | S87: Ajman Industrial | T87: SP-08 | U87: Ahmed Siddiqui | W87: 0 | Y87: Price / Budget
A88: L00087 | B88: Oasis Bright Motors LLC | C88: Facilities Management | D88: Medium (50-249) | E88: 24 | F88: Website | G88: Heavy Trucks | H88: 12 | I88: Yes | J88: 1.5M - 4M | K88: 3871000 | L88: Proposal | M88: 2025-01-13 | N88: 2026-03-07 | O88: 533 | P88: 11 | Q88: 115 | R88: Fujairah | S88: Dibba | T88: SP-03 | U88: Hassan Khoury | W88: 0
A89: L00088 | B89: Zenith Hicks Motors LLC | C89: Car Rental & Leasing | D89: Medium (50-249) | E89: 39 | F89: Referral | G89: Pickup Fleet | H89: 17 | I89: Yes | J89: 1.5M - 4M | K89: 1921000 | L89: Won | M89: 2026-02-13 | N89: 2026-06-29 | O89: 137 | P89: 6 | Q89: 1 | R89: Dubai | S89: Dubai South | T89: SP-06 | U89: Daniel Okafor | V89: 93 | W89: 1 | X89: 2026-05-17
A90: L00089 | B90: Horizon Davis Motors LLC | C90: Logistics & Transport | D90: Large (250-999) | E90: 103 | F90: LinkedIn | G90: Pickup Fleet | H90: 45 | I90: Yes | J90: 4M+ | K90: 5182000 | L90: Won | M90: 2025-03-11 | N90: 2026-03-20 | O90: 476 | P90: 4 | Q90: 102 | R90: Abu Dhabi | S90: Mussafah | T90: SP-03 | U90: Hassan Khoury | V90: 46 | W90: 1 | X90: 2025-04-26
A91: L00090 | B91: Nakheel Williams Motors LLC | C91: Car Rental & Leasing | D91: Medium (50-249) | E91: 29 | F91: LinkedIn | G91: Passenger Sedan Fleet | H91: 14 | I91: Yes | J91: 500K - 1.5M | K91: 1175000 | L91: Lost | M91: 2025-02-03 | N91: 2026-05-01 | O91: 512 | P91: 5 | Q91: 60 | R91: Dubai | S91: Al Quoz | T91: SP-05 | U91: Rashid Al Mansoori | W91: 0 | Y91: No Decision / Stalled
A92: L00091 | B92: Sahara Rodriguez Motors LLC | C92: Logistics & Transport | D92: Medium (50-249) | E92: 18 | F92: LinkedIn | G92: Light Commercial Vans | H92: 5 | I92: No | J92: < 500K | K92: 494000 | L92: Lost | M92: 2025-06-14 | N92: 2026-01-30 | O92: 381 | P92: 1 | Q92: 151 | R92: Dubai | S92: Jebel Ali | T92: SP-07 | U92: Mei Lin Tan | W92: 0 | Y92: Timing Deferred
A93: L00092 | B93: Crescent Burton Fleet Solutions | C93: Facilities Management | D93: Large (250-999) | E93: 72 | F93: Email | G93: Light Commercial Vans | H93: 39 | I93: Yes | J93: 1.5M - 4M | K93: 3713000 | L93: Lost | M93: 2024-10-03 | N93: 2026-04-03 | O93: 635 | P93: 2 | Q93: 88 | R93: Dubai | S93: Al Quoz | T93: SP-08 | U93: Ahmed Siddiqui | W93: 0 | Y93: No Decision / Stalled
A94: L00093 | B94: Pearl Conner Fleet Solutions | C94: Car Rental & Leasing | D94: Medium (50-249) | E94: 11 | F94: Partners | G94: Earth-Moving Equipment | H94: 6 | I94: Yes | J94: 1.5M - 4M | K94: 2744000 | L94: Won | M94: 2025-03-03 | N94: 2026-05-05 | O94: 484 | P94: 3 | Q94: 56 | R94: Dubai | S94: Deira | T94: SP-04 | U94: Elena Petrova | V94: 55 | W94: 1 | X94: 2025-04-27
A95: L00094 | B95: Cedar Henderson Fleet Solutions | C95: Car Rental & Leasing | D95: Small (<50) | E95: 11 | F95: LinkedIn | G95: Earth-Moving Equipment | H95: 4 | I95: Yes | J95: 1.5M - 4M | K95: 2065000 | L95: Lost | M95: 2026-01-03 | N95: 2026-06-29 | O95: 178 | P95: 5 | Q95: 1 | R95: Umm Al Quwain | S95: UAQ Industrial Area | T95: SP-03 | U95: Hassan Khoury | W95: 0 | Y95: Price / Budget
A96: L00095 | B96: Marina Brown Fleet Solutions | C96: Construction & Contracting | D96: Enterprise (1000+) | E96: 374 | F96: LinkedIn | G96: Bus Fleet | H96: 45 | I96: Yes | J96: 4M+ | K96: 11556000 | L96: Won | M96: 2025-08-24 | N96: 2026-04-25 | O96: 310 | P96: 8 | Q96: 66 | R96: Dubai | S96: Al Quoz | T96: SP-03 | U96: Hassan Khoury | V96: 40 | W96: 1 | X96: 2025-10-03
A97: L00096 | B97: Summit James Fleet Solutions | C97: Facilities Management | D97: Medium (50-249) | E97: 37 | F97: Trade Shows | G97: Heavy Trucks | H97: 10 | I97: Yes | J97: 1.5M - 4M | K97: 3386000 | L97: Proposal | M97: 2026-05-13 | N97: 2026-05-13 | O97: 48 | P97: 4 | Q97: 48 | R97: Ras Al Khaimah | S97: RAK Maritime City | T97: SP-02 | U97: Priya Nair | W97: 0
A98: L00097 | B98: Delta Ferrell Fleet Solutions | C98: Construction & Contracting | D98: Small (<50) | E98: 6 | F98: Referral | G98: Light Commercial Vans | H98: 3 | I98: Yes | J98: < 500K | K98: 284000 | L98: Won | M98: 2025-12-18 | N98: 2026-06-29 | O98: 194 | P98: 4 | Q98: 1 | R98: Dubai | S98: Dubai Investment Park | T98: SP-03 | U98: Hassan Khoury | V98: 26 | W98: 1 | X98: 2026-01-13
A99: L00098 | B99: Vertex Rice Fleet Solutions | C99: Logistics & Transport | D99: Medium (50-249) | E99: 26 | F99: Referral | G99: Earth-Moving Equipment | H99: 14 | I99: Yes | J99: 4M+ | K99: 7342000 | L99: Lost | M99: 2025-03-06 | N99: 2026-06-29 | O99: 481 | P99: 5 | Q99: 1 | R99: Abu Dhabi | S99: Al Ain | T99: SP-07 | U99: Mei Lin Tan | W99: 0 | Y99: Competitor Won
A100: L00099 | B100: Anchor Maddox Enterprises | C100: Logistics & Transport | D100: Small (<50) | E100: 14 | F100: Email | G100: Passenger Sedan Fleet | H100: 7 | I100: No | J100: 500K - 1.5M | K100: 577000 | L100: Proposal | M100: 2025-12-12 | N100: 2026-02-11 | O100: 200 | P100: 1 | Q100: 139 | R100: Abu Dhabi | S100: Khalifa Industrial Zone | T100: SP-04 | U100: Elena Petrova | W100: 0
...

Sheet Accounts Raw
A1: Account_ID | B1: Company_Name | C1: Industry | D1: Company_Size | E1: Fleet_Size | F1: Primary_Product | G1: Annual_Spend_AED | H1: Prev_Year_Spend_AED | I1: Spend_Growth_Pct | J1: Contract_Start | K1: Contract_Term_Years | L1: Contract_Expiry | M1: Contract_Age_Years | N1: Days_To_Expiry | O1: Last_Purchase_Date | P1: Days_Since_Last_Purchase | Q1: Days_Since_Last_Activity | R1: Service_Tickets_12M | S1: Avg_Satisfaction_Score | T1: Repeat_Issue_Rate | U1: Avg_Resolution_Days | V1: Competitor_Present | W1: Emirate | X1: City | Y1: Primary_Contact | Z1: Account_Manager_ID | AA1: Account_Manager | AB1: Account_Value_Tier | AC1: Churn_Status
A2: A00001 | B2: Gulf Atkinson Equipment LLC | C2: Oil & Gas Services | D2: Enterprise (1000+) | E2: 384 | F2: Pickup Fleet | G2: 3620000 | H2: 3253000 | I2: 11.3 | J2: 2024-10-06 | K2: 3 | L2: 2027-10-06 | M2: 1.73 | N2: 463 | O2: 2023-12-28 | P2: 915 | Q2: 26 | R2: 18 | S2: 3.97 | T2: 0.388 | U2: 2.7 | V2: No | W2: Sharjah | X2: Hamriyah Free Zone | Y2: Katherine Barton | Z2: SP-02 | AA2: Priya Nair | AB2: Gold | AC2: 0
A3: A00002 | B3: Emirates Turner Equipment LLC | C3: Retail Distribution | D3: Large (250-999) | E3: 56 | F3: Pickup Fleet | G3: 1264000 | H3: 864000 | I3: 46.3 | J3: 2023-01-19 | K3: 3 | L3: 2026-01-18 | M3: 3.44 | N3: -163 | O3: 2024-08-23 | P3: 676 | Q3: 26 | R3: 11 | S3: 3.09 | T3: 0.26 | U3: 4.8 | V3: Yes | W3: Dubai | X3: Al Quoz | Y3: Steven Hodges | Z3: SP-02 | AA3: Priya Nair | AB3: Silver | AC3: 1
A4: A00003 | B4: Al Noor Zimmerman Equipment LLC | C4: Construction & Contracting | D4: Medium (50-249) | E4: 43 | F4: Passenger Sedan Fleet | G4: 390000 | H4: 439000 | I4: -11.2 | J4: 2022-11-13 | K4: 2 | L4: 2024-11-12 | M4: 3.63 | N4: -595 | O4: 2023-04-25 | P4: 1162 | Q4: 28 | R4: 6 | S4: 4.44 | T4: 0.254 | U4: 3 | V4: No | W4: Ras Al Khaimah | X4: RAK Maritime City | Y4: Aaron Ortiz | Z4: SP-03 | AA4: Hassan Khoury | AB4: Bronze | AC4: 1
A5: A00004 | B5: Desert Shaffer Equipment LLC | C5: Oil & Gas Services | D5: Medium (50-249) | E5: 12 | F5: Light Commercial Vans | G5: 181000 | H5: 143000 | I5: 26.6 | J5: 2023-11-08 | K5: 2 | L5: 2025-11-07 | M5: 2.64 | N5: -235 | O5: 2025-09-05 | P5: 298 | Q5: 19 | R5: 1 | S5: 4.29 | T5: 0.103 | U5: 5.8 | V5: No | W5: Fujairah | X5: Fujairah Free Zone | Y5: Gregory Franco | Z5: SP-04 | AA5: Elena Petrova | AB5: Bronze | AC5: 0
A6: A00005 | B6: Falcon Melendez Equipment LLC | C6: Car Rental & Leasing | D6: Large (250-999) | E6: 49 | F6: Heavy Trucks | G6: 3462000 | H6: 3409000 | I6: 1.6 | J6: 2024-05-23 | K6: 2 | L6: 2026-05-23 | M6: 2.1 | N6: -38 | O6: 2025-09-12 | P6: 291 | Q6: 61 | R6: 4 | S6: 4.26 | T6: 0.174 | U6: 5.2 | V6: No | W6: Abu Dhabi | X6: Al Ain | Y6: Tiffany Smith | Z6: SP-04 | AA6: Elena Petrova | AB6: Gold | AC6: 0
A7: A00006 | B7: Arabian Hart Freight LLC | C7: Hospitality & Tourism | D7: Medium (50-249) | E7: 17 | F7: Bus Fleet | G7: 660000 | H7: 543000 | I7: 21.5 | J7: 2025-05-08 | K7: 2 | L7: 2027-05-08 | M7: 1.14 | N7: 312 | O7: 2025-12-18 | P7: 194 | Q7: 82 | R7: 4 | S7: 4.08 | T7: 0.131 | U7: 4.1 | V7: No | W7: Dubai | X7: Deira | Y7: Sarah Acosta | Z7: SP-06 | AA7: Daniel Okafor | AB7: Silver | AC7: 0
A8: A00007 | B8: Oasis Faulkner Freight LLC | C8: Retail Distribution | D8: Enterprise (1000+) | E8: 247 | F8: Light Commercial Vans | G8: 2992000 | H8: 2101000 | I8: 42.4 | J8: 2022-03-20 | K8: 4 | L8: 2026-03-19 | M8: 4.28 | N8: -103 | O8: 2025-03-15 | P8: 472 | Q8: 11 | R8: 12 | S8: 3.77 | T8: 0.341 | U8: 1 | V8: Yes | W8: Abu Dhabi | X8: Khalifa Industrial Zone | Y8: Joseph Allen | Z8: SP-04 | AA8: Elena Petrova | AB8: Gold | AC8: 1
A9: A00008 | B9: Zenith Grant Freight LLC | C9: Hospitality & Tourism | D9: Enterprise (1000+) | E9: 248 | F9: SUV Fleet | G9: 5889000 | H9: 6062000 | I9: -2.9 | J9: 2025-07-02 | K9: 4 | L9: 2029-07-01 | M9: 0.99 | N9: 1097 | O9: 2025-10-03 | P9: 270 | Q9: 21 | R9: 12 | S9: 3.46 | T9: 0.222 | U9: 3.7 | V9: Yes | W9: Dubai | X9: Al Quoz | Y9: Anthony Shea DDS | Z9: SP-02 | AA9: Priya Nair | AB9: Platinum | AC9: 0
A10: A00009 | B10: Horizon Anderson Freight LLC | C10: Retail Distribution | D10: Large (250-999) | E10: 69 | F10: Light Commercial Vans | G10: 933000 | H10: 602000 | I10: 55 | J10: 2022-10-25 | K10: 3 | L10: 2025-10-24 | M10: 3.68 | N10: -249 | O10: 2023-11-06 | P10: 967 | Q10: 13 | R10: 9 | S10: 3.38 | T10: 0.22 | U10: 3.3 | V10: Yes | W10: Abu Dhabi | X10: Al Ain | Y10: Thomas Merritt | Z10: SP-03 | AA10: Hassan Khoury | AB10: Silver | AC10: 1
A11: A00010 | B11: Nakheel Sanchez Freight LLC | C11: Facilities Management | D11: Medium (50-249) | E11: 18 | F11: Heavy Trucks | G11: 584000 | H11: 484000 | I11: 20.7 | J11: 2024-02-03 | K11: 3 | L11: 2027-02-02 | M11: 2.4 | N11: 217 | O11: 2026-01-25 | P11: 156 | Q11: 7 | R11: 4 | S11: 3.98 | T11: 0.129 | U11: 5.5 | V11: No | W11: Sharjah | X11: Al Sajaa | Y11: Mercedes Watson | Z11: SP-04 | AA11: Elena Petrova | AB11: Bronze | AC11: 0
A12: A00011 | B12: Sahara Harris Freight LLC | C12: Logistics & Transport | D12: Large (250-999) | E12: 96 | F12: Light Commercial Vans | G12: 1096000 | H12: 651000 | I12: 68.4 | J12: 2024-09-29 | K12: 3 | L12: 2027-09-29 | M12: 1.75 | N12: 456 | O12: 2023-06-10 | P12: 1116 | Q12: 50 | R12: 5 | S12: 3.65 | T12: 0.136 | U12: 4.1 | V12: No | W12: Dubai | X12: Al Quoz | Y12: Angela Davis | Z12: SP-05 | AA12: Rashid Al Mansoori | AB12: Silver | AC12: 1
A13: A00012 | B13: Crescent Lucas Freight LLC | C13: Government & Municipal | D13: Large (250-999) | E13: 74 | F13: Passenger Sedan Fleet | G13: 1689000 | H13: 1986000 | I13: -15 | J13: 2024-01-17 | K13: 2 | L13: 2026-01-16 | M13: 2.45 | N13: -165 | O13: 2025-11-03 | P13: 239 | Q13: 8 | R13: 8 | S13: 3.36 | T13: 0.204 | U13: 4.6 | V13: Yes | W13: Fujairah | X13: Dibba | Y13: Robert Jones | Z13: SP-08 | AA13: Ahmed Siddiqui | AB13: Silver | AC13: 0
... A721: A00720 | B721: Meridian Marshall Services FZE | C721: Logistics & Transport | D721: Large (250-999) | E721: 52 | F721: Bus Fleet | G721: 3049000 | H721: 5223000 | I721: -41.6 | J721: 2024-12-12 | K721: 5 | L721: 2029-12-11 | M721: 1.55 | N721: 1260 | O721: 2026-03-12 | P721: 110 | Q721: 62 | R721: 5 | S721: 3.73 | T721: 0.154 | U721: 4 | V721: No | W721: Ajman | X721: Al Jurf | Y721: Marcus King | Z721: SP-07 | AA721: Mei Lin Tan | AB721: Gold | AC721: 0

Sheet Activities Raw
A1: Activity_ID | B1: Account_ID | C1: Lead_ID | D1: Activity_Type | E1: Activity_Date | F1: Duration_Minutes | G1: Outcome | H1: Salesperson_ID | I1: Notes
A2: ACT000001 | C2: L00001 | D2: Meeting | E2: 2025-03-08 | F2: 54 | G2: No Response | H2: SP-08 | I2: Meeting logged for Gulf Fowler Logistics LLC
A3: ACT000002 | C3: L00001 | D3: Call | E3: 2025-02-13 | F3: 14 | G3: Follow-up Required | H3: SP-08 | I3: Call logged for Gulf Fowler Logistics LLC
A4: ACT000003 | C4: L00002 | D4: Demo | E4: 2025-07-10 | F4: 64 | G4: No Response | H4: SP-08 | I4: Demo logged for Emirates Johnson Logistics LLC
A5: ACT000004 | C5: L00002 | D5: Call | E5: 2025-10-30 | F5: 14 | G5: Positive | H5: SP-08 | I5: Call logged for Emirates Johnson Logistics LLC
A6: ACT000005 | C6: L00002 | D6: Proposal | E6: 2026-05-17 | F6: 38 | G6: Follow-up Required | H6: SP-08 | I6: Proposal logged for Emirates Johnson Logistics LLC
A7: ACT000006 | C7: L00002 | D7: Meeting | E7: 2024-12-18 | F7: 63 | G7: Positive | H7: SP-08 | I7: Meeting logged for Emirates Johnson Logistics LLC
A8: ACT000007 | C8: L00002 | D8: Call | E8: 2025-09-07 | F8: 31 | G8: Neutral | H8: SP-08 | I8: Call logged for Emirates Johnson Logistics LLC
A9: ACT000008 | C9: L00003 | D9: Call | E9: 2026-03-05 | F9: 20 | G9: No Response | H9: SP-05 | I9: Call logged for Al Noor Hill Logistics LLC
A10: ACT000009 | C10: L00003 | D10: Call | E10: 2025-06-14 | F10: 10 | G10: Positive | H10: SP-05 | I10: Call logged for Al Noor Hill Logistics LLC
A11: ACT000010 | C11: L00003 | D11: Meeting | E11: 2025-09-09 | F11: 49 | G11: Neutral | H11: SP-05 | I11: Meeting logged for Al Noor Hill Logistics LLC
A12: ACT000011 | C12: L00003 | D12: Meeting | E12: 2025-03-21 | F12: 51 | G12: Follow-up Required | H12: SP-05 | I12: Meeting logged for Al Noor Hill Logistics LLC
A13: ACT000012 | C13: L00003 | D13: Call | E13: 2025-09-25 | F13: 7 | G13: Neutral | H13: SP-05 | I13: Call logged for Al Noor Hill Logistics LLC
... A8522: ACT008521 | C8522: L02000 | D8522: Call | E8522: 2026-03-28 | F8522: 9 | G8522: Neutral | H8522: SP-08 | I8522: Call logged for Gulf Wells Rentals LLC
A8523: ACT008522 | B8523: A00001 | D8523: Call | E8523: 2025-06-01 | F8523: 20 | G8523: Follow-up Required | H8523: SP-02 | I8523: Account touchpoint - Call
A8524: ACT008523 | B8524: A00001 | D8524: Meeting | E8524: 2025-07-16 | F8524: 38 | G8524: Positive | H8524: SP-02 | I8524: Account touchpoint - Meeting
A8525: ACT008524 | B8525: A00002 | D8525: Email | E8525: 2025-06-26 | F8525: 36 | G8525: No Response | H8525: SP-02 | I8525: Account touchpoint - Email
A8526: ACT008525 | B8526: A00002 | D8526: Email | E8526: 2025-11-15 | F8526: 26 | G8526: Follow-up Required | H8526: SP-02 | I8526: Account touchpoint - Email
A8527: ACT008526 | B8527: A00003 | D8527: Call | E8527: 2026-01-19 | F8527: 34 | G8527: No Response | H8527: SP-03 | I8527: Account touchpoint - Call
A8528: ACT008527 | B8528: A00003 | D8528: Call | E8528: 2025-11-01 | F8528: 15 | G8528: Neutral | H8528: SP-03 | I8528: Account touchpoint - Call
A8529: ACT008528 | B8529: A00003 | D8529: Call | E8529: 2025-07-03 | F8529: 16 | G8529: No Response | H8529: SP-03 | I8529: Account touchpoint - Call
A8530: ACT008529 | B8530: A00003 | D8530: Call | E8530: 2026-05-13 | F8530: 25 | G8530: Neutral | H8530: SP-03 | I8530: Account touchpoint - Call
A8531: ACT008530 | B8531: A00003 | D8531: Call | E8531: 2025-09-04 | F8531: 19 | G8531: Neutral | H8531: SP-03 | I8531: Account touchpoint - Call
A8532: ACT008531 | B8532: A00003 | D8532: Call | E8532: 2026-04-17 | F8532: 23 | G8532: Positive | H8532: SP-03 | I8532: Account touchpoint - Call
A8533: ACT008532 | B8533: A00004 | D8533: Call | E8533: 2026-05-12 | F8533: 26 | G8533: Positive | H8533: SP-04 | I8533: Account touchpoint - Call
A8534: ACT008533 | B8534: A00004 | D8534: Demo | E8534: 2025-12-10 | F8534: 33 | G8534: Neutral | H8534: SP-04 | I8534: Account touchpoint - Demo
... A11398: ACT011397 | B11398: A00720 | D11398: Meeting | E11398: 2025-09-09 | F11398: 13 | G11398: Positive | H11398: SP-07 | I11398: Account touchpoint - Meeting

Sheet Service Raw
A1: Service_ID | B1: Account_ID | C1: Service_Date | D1: Service_Type | E1: Satisfaction_Score | F1: Issue_Category | G1: Resolution_Time_Days | H1: Repeat_Issue | I1: Cost_AED
A2: SR000001 | B2: A00001 | C2: 2025-07-27 | D2: Corrective | E2: 5 | F2: Warranty Claim | G2: 4.3 | H2: No | I2: 250
A3: SR000002 | B3: A00001 | C3: 2026-05-29 | D3: Corrective | E3: 4 | F3: Parts Availability | G3: 1.2 | H3: No | I3: 5785.61
A4: SR000003 | B4: A00001 | C4: 2025-07-03 | D4: Preventive | E4: 4 | F4: Telematics / Software | G4: 5.1 | H4: No | I4: 3012.25
A5: SR000004 | B5: A00001 | C5: 2026-01-01 | D5: Preventive | E5: 4 | F5: Mechanical Fault | G5: 2.2 | H5: No | I5: 5149.16
A6: SR000005 | B6: A00001 | C6: 2025-11-18 | D6: Corrective | E6: 4 | F6: Parts Availability | G6: 1.4 | H6: No | I6: 6264.39
A7: SR000006 | B7: A00001 | C7: 2025-11-11 | D7: Preventive | E7: 4 | F7: Downtime / SLA Breach | G7: 3.3 | H7: Yes | I7: 6544.47
A8: SR000007 | B8: A00001 | C8: 2026-03-16 | D8: Preventive | E8: 3 | F8: Parts Availability | G8: 2.6 | H8: No | I8: 4912.6
A9: SR000008 | B9: A00001 | C9: 2026-01-08 | D9: Emergency | E9: 4 | F9: Downtime / SLA Breach | G9: 2.8 | H9: No | I9: 4291.58
A10: SR000009 | B10: A00001 | C10: 2025-12-17 | D10: Warranty | E10: 4 | F10: Scheduled Maintenance | G10: 1.6 | H10: No | I10: 3576.22
A11: SR000010 | B11: A00001 | C11: 2025-07-30 | D11: Emergency | E11: 3 | F11: Downtime / SLA Breach | G11: 0.7 | H11: No | I11: 4399.32
A12: SR000011 | B12: A00001 | C12: 2026-05-05 | D12: Preventive | E12: 4 | F12: Parts Availability | G12: 3.4 | H12: Yes | I12: 5304.82
A13: SR000012 | B13: A00001 | C13: 2026-01-28 | D13: Preventive | E13: 3 | F13: Warranty Claim | G13: 0.9 | H13: No | I13: 6103.39
... A4252: SR004251 | B4252: A00720 | C4252: 2026-01-27 | D4252: Corrective | E4252: 3 | F4252: Scheduled Maintenance | G4252: 3.7 | H4252: No | I4252: 8431.53

Sheet Data Dictionary
A1: Table | B1: Column | C1: Data_Type | D1: Business_Meaning
A2: Leads | B2: Lead_ID | C2: str | D2: Unique CRM lead identifier
A3: Leads | B3: Company_Name | C3: str | D3: Synthetic company name
A4: Leads | B4: Industry | C4: str | D4: Customer vertical
A5: Leads | B5: Company_Size | C5: str | D5: Employee band
A6: Leads | B6: Fleet_Size | C6: int64 | D6: Vehicles operated
A7: Leads | B7: Lead_Source | C7: str | D7: Marketing channel that generated the lead
A8: Leads | B8: Product_Interest | C8: str | D8: Vehicle category requested
A9: Leads | B9: Units_Requested | C9: int64 | D9: Vehicles in the enquiry
A10: Leads | B10: Budget_Allocated | C10: str | D10: Budget signed off (Yes/No)
A11: Leads | B11: Budget_Range | C11: str | D11: Deal value band
A12: Leads | B12: Deal_Value_AED | C12: float64 | D12: Estimated contract value
... A73: Service | B73: Cost_AED | C73: float64 | D73: Service cost

Sheet Lead Scoring
A1: Lead_ID | B1: Company_Name | C1: Industry | D1: Emirate | E1: City | F1: Lead_Source | G1: Product_Interest | H1: Company_Size | I1: Fleet_Size | J1: Deal_Value_AED | K1: Sales_Stage | L1: Days_in_Pipeline | M1: Number_of_Sales_Calls | N1: Days_Since_Last_Contact | O1: Salesperson | P1: Lead_Score | Q1: Lead_Priority | R1: Expected_Value_AED | S1: Recommended_Action
A2: L00656 | B2: Delta Jones Rentals LLC | C2: Construction & Contracting | D2: Dubai | E2: Jebel Ali | F2: Partners | G2: Heavy Trucks | H2: Enterprise (1000+) | I2: 399 | J2: 14125000 | K2: Won | L2: 80 | M2: 11 | N2: 1 | O2: Omar Al Farsi | P2: 99 | Q2: Very High | R2: 13983512 | S2: Call within 24h - route to senior AE, prepare fleet proposal
A3: L00768 | B3: Horizon Martinez Industries LLC | C3: Logistics & Transport | D3: Umm Al Quwain | E3: UAQ Industrial Area | F3: Referral | G3: Heavy Trucks | H3: Large (250-999) | I3: 107 | J3: 14208000 | K3: Won | L3: 172 | M3: 8 | N3: 113 | O3: Rashid Al Mansoori | P3: 98.2 | Q3: Very High | R3: 13951348 | S3: Call within 24h - route to senior AE, prepare fleet proposal
A4: L00436 | B4: Summit Williams Transport Co | C4: Construction & Contracting | D4: Ajman | E4: Ajman Industrial | F4: Referral | G4: Heavy Trucks | H4: Enterprise (1000+) | I4: 353 | J4: 15635000 | K4: Won | L4: 88 | M4: 5 | N4: 88 | O4: Hassan Khoury | P4: 98.2 | Q4: Very High | R4: 15360599 | S4: Call within 24h - route to senior AE, prepare fleet proposal
A5: L00310 | B5: Nakheel Valencia Enterprises | C5: Logistics & Transport | D5: Umm Al Quwain | E5: UAQ Industrial Area | F5: Referral | G5: Passenger Sedan Fleet | H5: Enterprise (1000+) | I5: 129 | J5: 3893000 | K5: Won | L5: 154 | M5: 5 | N5: 2 | O5: Omar Al Farsi | P5: 98 | Q5: Very High | R5: 3813228 | S5: Call within 24h - route to senior AE, prepare fleet proposal
A6: L01596 | B6: Oasis Elliott Industries LLC | C6: Facilities Management | D6: Abu Dhabi | E6: Khalifa Industrial Zone | F6: Referral | G6: SUV Fleet | H6: Enterprise (1000+) | I6: 366 | J6: 7317000 | K6: Won | L6: 95 | M6: 7 | N6: 34 | O6: Rashid Al Mansoori | P6: 97.7 | Q6: Very High | R6: 7145177 | S6: Call within 24h - route to senior AE, prepare fleet proposal
A7: L01599 | B7: Nakheel Williams Industries LLC | C7: Retail Distribution | D7: Sharjah | E7: Al Sajaa | F7: Referral | G7: Heavy Trucks | H7: Enterprise (1000+) | I7: 255 | J7: 14228000 | K7: Won | L7: 94 | M7: 3 | N7: 94 | O7: Rashid Al Mansoori | P7: 97.6 | Q7: Very High | R7: 13881820 | S7: Call within 24h - route to senior AE, prepare fleet proposal
A8: L01887 | B8: Oasis Miller Transport Co | C8: Logistics & Transport | D8: Sharjah | E8: Industrial Area | F8: Trade Shows | G8: Pickup Fleet | H8: Enterprise (1000+) | I8: 340 | J8: 5342000 | K8: Won | L8: 112 | M8: 4 | N8: 56 | O8: Elena Petrova | P8: 97.2 | Q8: Very High | R8: 5189988 | S8: Call within 24h - route to senior AE, prepare fleet proposal
A9: L00227 | B9: Oasis Shaw Transport Co | C9: Logistics & Transport | D9: Sharjah | E9: Al Sajaa | F9: Referral | G9: Heavy Trucks | H9: Large (250-999) | I9: 45 | J9: 7481000 | K9: Won | L9: 142 | M9: 5 | N9: 17 | O9: Omar Al Farsi | P9: 97.2 | Q9: Very High | R9: 7270453 | S9: Call within 24h - route to senior AE, prepare fleet proposal
A10: L01895 | B10: Marina Meyer Rentals LLC | C10: Construction & Contracting | D10: Abu Dhabi | E10: Mussafah | F10: LinkedIn | G10: Heavy Trucks | H10: Enterprise (1000+) | I10: 263 | J10: 14634000 | K10: Won | L10: 136 | M10: 13 | N10: 78 | O10: Rashid Al Mansoori | P10: 96.7 | Q10: Very High | R10: 14152436 | S10: Call within 24h - route to senior AE, prepare fleet proposal
A11: L01110 | B11: Pearl Douglas Holdings | C11: Logistics & Transport | D11: Abu Dhabi | E11: Khalifa Industrial Zone | F11: Partners | G11: Light Commercial Vans | H11: Enterprise (1000+) | I11: 343 | J11: 4676000 | K11: Won | L11: 67 | M11: 5 | N11: 1 | O11: Hassan Khoury | P11: 96.7 | Q11: Very High | R11: 4520165 | S11: Call within 24h - route to senior AE, prepare fleet proposal
A12: L00404 | B12: Desert Santana Motors LLC | C12: Logistics & Transport | D12: Ras Al Khaimah | E12: RAK Maritime City | F12: Trade Shows | G12: Earth-Moving Equipment | H12: Enterprise (1000+) | I12: 218 | J12: 20986000 | K12: Won | L12: 217 | M12: 7 | N12: 74 | O12: Priya Nair | P12: 96.6 | Q12: Very High | R12: 20274583 | S12: Call within 24h - route to senior AE, prepare fleet proposal
A13: L00651 | B13: Crescent Williams Rentals LLC | C13: Car Rental & Leasing | D13: Dubai | E13: Dubai Investment Park | F13: Partners | G13: Passenger Sedan Fleet | H13: Enterprise (1000+) | I13: 181 | J13: 3243000 | K13: Won | L13: 131 | M13: 9 | N13: 1 | O13: Omar Al Farsi | P13: 96.4 | Q13: Very High | R13: 3125641 | S13: Call within 24h - route to senior AE, prepare fleet proposal
... A2001: L00981 | B2001: Desert Chavez Group | C2001: Hospitality & Tourism | D2001: Abu Dhabi | E2001: Al Ain | F2001: Outbound | G2001: Bus Fleet | H2001: Medium (50-249) | I2001: 17 | J2001: 742000 | K2001: Lost | L2001: 715 | M2001: 2 | N2001: 117 | O2001: Daniel Okafor | P2001: 0.8 | Q2001: Low | R2001: 5870 | S2001: Automated nurture only - do not consume field-sales capacity

Sheet Top 50 Leads
A1: TOP 50 PRIORITY LEADS - OPEN PIPELINE, RANKED BY MODEL SCORE x DEAL VALUE
A3: Rank | B3: Lead_ID | C3: Company_Name | D3: Industry | E3: Emirate | F3: Lead_Source | G3: Product_Interest | H3: Deal_Value_AED | I3: Lead_Score | J3: Lead_Priority | K3: Expected_Value_AED | L3: Sales_Stage | M3: Last_Contact_Date | N3: Days_Since_Last_Contact | O3: Salesperson | P3: Recommended_Action
A4: 1 | B4: L01708 | C4: Al Noor Wells Trading LLC | D4: Car Rental & Leasing | E4: Fujairah | F4: Partners | G4: Heavy Trucks | H4: 13391000 | I4: 94.8 | J4: Very High | K4: 12697788 | L4: Proposal | M4: 2026-04-16 | N4: 75 | O4: Rashid Al Mansoori | P4: Call within 24h - route to senior AE, prepare fleet proposal
A5: 2 | B5: L00301 | C5: Gulf Mckee Motors LLC | D5: Retail Distribution | E5: Sharjah | F5: Website | G5: Pickup Fleet | H5: 5028000 | I5: 93.8 | J5: Very High | K5: 4718169 | L5: Qualified | M5: 2026-05-21 | N5: 40 | O5: Omar Al Farsi | P5: Call within 24h - route to senior AE, prepare fleet proposal
A6: 3 | B6: L00766 | C6: Oasis Kim Industries LLC | D6: Logistics & Transport | E6: Abu Dhabi | F6: Trade Shows | G6: Passenger Sedan Fleet | H6: 3329000 | I6: 91.6 | J6: Very High | K6: 3048852 | L6: Proposal | M6: 2026-02-13 | N6: 137 | O6: Omar Al Farsi | P6: Call within 24h - route to senior AE, prepare fleet proposal
A7: 4 | B7: L00438 | C7: Vertex Charles Transport Co | D7: Car Rental & Leasing | E7: Ajman | F7: LinkedIn | G7: Pickup Fleet | H7: 3259000 | I7: 89.7 | J7: Very High | K7: 2922299 | L7: Prospect | M7: 2026-05-21 | N7: 40 | O7: Daniel Okafor | P7: Call within 24h - route to senior AE, prepare fleet proposal
A8: 5 | B8: L00213 | C8: Pearl Gibson Logistics LLC | D8: Logistics & Transport | E8: Sharjah | F8: Website | G8: Heavy Trucks | H8: 15509000 | I8: 88.8 | J8: Very High | K8: 13777075 | L8: Negotiation | M8: 2026-06-25 | N8: 5 | O8: Ahmed Siddiqui | P8: Call within 24h - route to senior AE, prepare fleet proposal
A9: 6 | B9: L00057 | C9: Delta Jackson Holdings | D9: Car Rental & Leasing | E9: Abu Dhabi | F9: Trade Shows | G9: Light Commercial Vans | H9: 4261000 | I9: 88.2 | J9: Very High | K9: 3757773 | L9: Proposal | M9: 2026-06-29 | N9: 1 | O9: Mei Lin Tan | P9: Call within 24h - route to senior AE, prepare fleet proposal
A10: 7 | B10: L01448 | C10: Cedar Mahoney Motors LLC | D10: Oil & Gas Services | E10: Abu Dhabi | F10: Trade Shows | G10: Pickup Fleet | H10: 2298000 | I10: 88.1 | J10: Very High | K10: 2024469 | L10: Negotiation | M10: 2026-06-15 | N10: 15 | O10: Daniel Okafor | P10: Call within 24h - route to senior AE, prepare fleet proposal
A11: 8 | B11: L01810 | C11: Zenith Thompson Trading LLC | D11: Logistics & Transport | E11: Ajman | F11: Email | G11: Light Commercial Vans | H11: 3357000 | I11: 87.5 | J11: Very High | K11: 2937714 | L11: Proposal | M11: 2026-05-18 | N11: 43 | O11: Elena Petrova | P11: Call within 24h - route to senior AE, prepare fleet proposal
A12: 9 | B12: L00437 | C12: Delta Wright Transport Co | D12: Logistics & Transport | E12: Abu Dhabi | F12: Partners | G12: Heavy Trucks | H12: 1407000 | I12: 87.3 | J12: Very High | K12: 1227799 | L12: Negotiation | M12: 2026-03-20 | N12: 102 | O12: Elena Petrova | P12: Call within 24h - route to senior AE, prepare fleet proposal
A13: 10 | B13: L00180 | C13: Meridian Owens Freight LLC | D13: Retail Distribution | E13: Abu Dhabi | F13: Outbound | G13: Heavy Trucks | H13: 14256000 | I13: 87.2 | J13: Very High | K13: 12429823 | L13: Qualified | M13: 2026-06-29 | N13: 1 | O13: Mei Lin Tan | P13: Call within 24h - route to senior AE, prepare fleet proposal
A14: 11 | B14: L01888 | C14: Zenith Elliott Transport Co | D14: Logistics & Transport | E14: Ajman | F14: LinkedIn | G14: Pickup Fleet | H14: 2961000 | I14: 85.6 | J14: Very High | K14: 2534915 | L14: Qualified | M14: 2026-05-14 | N14: 47 | O14: Ahmed Siddiqui | P14: Call within 24h - route to senior AE, prepare fleet proposal
A15: 12 | B15: L00140 | C15: Meridian Anderson Industries LLC | D15: Logistics & Transport | E15: Dubai | F15: Email | G15: Heavy Trucks | H15: 2484000 | I15: 85.2 | J15: Very High | K15: 2115708 | L15: Proposal | M15: 2026-06-29 | N15: 1 | O15: Omar Al Farsi | P15: Call within 24h - route to senior AE, prepare fleet proposal
... A53: 50 | B53: L01262 | C53: Oasis Wagner Logistics LLC | D53: Car Rental & Leasing | E53: Dubai | F53: Referral | G53: SUV Fleet | H53: 7043000 | I53: 72.2 | J53: Very High | K53: 5082371 | L53: Proposal | M53: 2026-05-29 | N53: 32 | O53: Elena Petrova | P53: Call within 24h - route to senior AE, prepare fleet proposal

Sheet Churn Prediction
A1: Account_ID | B1: Company_Name | C1: Industry | D1: Emirate | E1: Account_Value_Tier | F1: Fleet_Size | G1: Annual_Spend_AED | H1: Contract_Expiry | I1: Days_To_Expiry | J1: Avg_Satisfaction_Score | K1: Service_Tickets_12M | L1: Competitor_Present | M1: Days_Since_Last_Purchase | N1: Churn_Probability | O1: Risk_Category | P1: Revenue_at_Risk_AED | Q1: Churn_Drivers | R1: Retention_Action | S1: Account_Manager
A2: A00250 | B2: Nakheel Flores Enterprises | C2: Construction & Contracting | D2: Dubai | E2: Gold | F2: 387 | G2: 4263000 | H2: 2030-04-23 | I2: 1393 | J2: 2.56 | K2: 23 | L2: Yes | M2: 747 | N2: 92.6 | O2: Critical | P2: =G2*N2/100 -> 3947538 | Q2: Competitor active in account; Low satisfaction (2.6/5); High service load (23 tickets); Repeat failures (57%) | R2: ESCALATE: commercial director call within 7 days; service-recovery plan + retention offer on renewal | S2: Omar Al Farsi
A3: A00263 | B3: Al Noor Long Contracting LLC | C3: Oil & Gas Services | D3: Sharjah | E3: Platinum | F3: 379 | G3: 5537000 | H3: 2028-07-04 | I3: 735 | J3: 3.1 | K3: 18 | L3: Yes | M3: 255 | N3: 92.6 | O3: Critical | P3: =G3*N3/100 -> 5127262 | Q3: Competitor active in account; Low satisfaction (3.3/5); High service load (18 tickets); Repeat failures (28%) | R3: ESCALATE: commercial director call within 7 days; service-recovery plan + retention offer on renewal | S3: Daniel Okafor
A4: A00555 | B4: Marina Reyes Fleet Solutions | C4: Car Rental & Leasing | D4: Fujairah | E4: Gold | F4: 374 | G4: 2171000 | H4: 2025-01-13 | I4: -533 | J4: 1.98 | K4: 29 | L4: Yes | M4: 1558 | N4: 92.6 | O4: Critical | P4: =G4*N4/100 -> 2010346 | Q4: Competitor active in account; Low satisfaction (2.0/5); High service load (29 tickets); Repeat failures (62%) | R4: ESCALATE: commercial director call within 7 days; service-recovery plan + retention offer on renewal | S4: Omar Al Farsi
A5: A00277 | B5: Delta Flynn Rentals LLC | C5: Hospitality & Tourism | D5: Fujairah | E5: Platinum | F5: 311 | G5: 8098000 | H5: 2029-02-03 | I5: 949 | J5: 3.19 | K5: 18 | L5: Yes | M5: 461 | N5: 92.6 | O5: Critical | P5: =G5*N5/100 -> 7498748 | Q5: Competitor active in account; Low satisfaction (3.1/5); High service load (18 tickets); Repeat failures (56%) | R5: ESCALATE: commercial director call within 7 days; service-recovery plan + retention offer on renewal | S5: Rashid Al Mansoori
A6: A00056 | B6: Summit Walker Transport Co | C6: Facilities Management | D6: Sharjah | E6: Gold | F6: 278 | G6: 2894000 | H6: 2027-08-14 | I6: 410 | J6: 2.68 | K6: 10 | L6: Yes | M6: 1668 | N6: 92.6 | O6: Critical | P6: =G6*N6/100 -> 2679844 | Q6: Competitor active in account; Low satisfaction (2.9/5); High service load (10 tickets); No purchase in 1668d | R6: ESCALATE: commercial director call within 7 days; service-recovery plan + retention offer on renewal | S6: Mei Lin Tan
A7: A00103 | B7: Al Noor Moreno Holdings | C7: Oil & Gas Services | D7: Dubai | E7: Platinum | F7: 316 | G7: 7480000 | H7: 2025-04-04 | I7: -452 | J7: 3.25 | K7: 17 | L7: Yes | M7: 480 | N7: 92.6 | O7: Critical | P7: =G7*N7/100 -> 6926480 | Q7: Competitor active in account; Low satisfaction (3.2/5); High service load (17 tickets); Repeat failures (29%) | R7: ESCALATE: commercial director call within 7 days; service-recovery plan + retention offer on renewal | S7: Elena Petrova
A8: A00054 | B8: Cedar Gutierrez Contracting LLC | C8: Retail Distribution | D8: Dubai | E8: Platinum | F8: 365 | G8: 8485000 | H8: 2023-08-31 | I8: -1034 | J8: 3.53 | K8: 17 | L8: No | M8: 831 | N8: 92.6 | O8: Critical | P8: =G8*N8/100 -> 7857110 | Q8: Low satisfaction (3.4/5); High service load (17 tickets); Repeat failures (29%); No purchase in 831d | R8: ESCALATE: commercial director call within 7 days; service-recovery plan + retention offer on renewal | S8: Omar Al Farsi
A9: A00055 | B9: Marina Hart Transport Co | C9: Retail Distribution | D9: Sharjah | E9: Gold | F9: 291 | G9: 2151000 | H9: 2025-03-06 | I9: -481 | J9: 3.08 | K9: 12 | L9: Yes | M9: 1783 | N9: 92.6 | O9: Critical | P9: =G9*N9/100 -> 1991826 | Q9: Competitor active in account; Low satisfaction (3.2/5); High service load (12 tickets); No purchase in 1783d | R9: ESCALATE: commercial director call within 7 days; service-recovery plan + retention offer on renewal | S9: Daniel Okafor
A10: A00150 | B10: Nakheel Lam Logistics LLC | C10: Logistics & Transport | D10: Sharjah | E10: Silver | F10: 384 | G10: 1717000 | H10: 2025-10-31 | I10: -242 | J10: 2.75 | K10: 19 | L10: Yes | M10: 796 | N10: 92.6 | O10: Critical | P10: =G10*N10/100 -> 1589942 | Q10: Competitor active in account; Low satisfaction (2.5/5); High service load (19 tickets); Repeat failures (58%) | R10: ESCALATE: commercial director call within 7 days; service-recovery plan + retention offer on renewal | S10: Ahmed Siddiqui
A11: A00224 | B11: Desert James Facilities LLC | C11: Hospitality & Tourism | D11: Ras Al Khaimah | E11: Gold | F11: 319 | G11: 2814000 | H11: 2026-11-09 | I11: 132 | J11: 3.05 | K11: 15 | L11: Yes | M11: 1099 | N11: 92.6 | O11: Critical | P11: =G11*N11/100 -> 2605764 | Q11: Competitor active in account; Low satisfaction (3.1/5); High service load (15 tickets); Repeat failures (33%) | R11: ESCALATE: commercial director call within 7 days; service-recovery plan + retention offer on renewal | S11: Daniel Okafor
A12: A00223 | B12: Al Noor Jackson Facilities LLC | C12: Construction & Contracting | D12: Abu Dhabi | E12: Gold | F12: 344 | G12: 2833000 | H12: 2025-03-06 | I12: -481 | J12: 2.85 | K12: 17 | L12: Yes | M12: 458 | N12: 92.6 | O12: Critical | P12: =G12*N12/100 -> 2623358 | Q12: Competitor active in account; Low satisfaction (3.1/5); High service load (17 tickets); Repeat failures (53%) | R12: ESCALATE: commercial director call within 7 days; service-recovery plan + retention offer on renewal | S12: Hassan Khoury
A13: A00431 | B13: Sahara Richardson Freight LLC | C13: Car Rental & Leasing | D13: Abu Dhabi | E13: Gold | F13: 384 | G13: 3511000 | H13: 2025-11-12 | I13: -230 | J13: 2.93 | K13: 25 | L13: Yes | M13: 796 | N13: 92.6 | O13: Critical | P13: =G13*N13/100 -> 3251186 | Q13: Competitor active in account; Low satisfaction (3.0/5); High service load (25 tickets); Repeat failures (48%) | R13: ESCALATE: commercial director call within 7 days; service-recovery plan + retention offer on renewal | S13: Mei Lin Tan
... A721: A00083 | B721: Al Noor Johnson Trading LLC | C721: Car Rental & Leasing | D721: Ras Al Khaimah | E721: Bronze | F721: 25 | G721: 553000 | H721: 2027-10-13 | I721: 470 | J721: 4.59 | K721: 1 | L721: No | M721: 116 | N721: 0 | O721: Low | P721: =G721*N721/100 -> 0 | Q721: No material risk signal | R721: Business as usual - keep in standard care programme | S721: Daniel Okafor

Sheet Revenue at Risk
A1: REVENUE AT RISK = ANNUAL SPEND x CHURN PROBABILITY (RANKED BY EXPOSURE)
A3: Rank | B3: Account_ID | C3: Company_Name | D3: Industry | E3: Emirate | F3: Account_Value_Tier | G3: Fleet_Size | H3: Annual_Spend_AED | I3: Churn_Probability | J3: Revenue_at_Risk_AED | K3: Risk_Category | L3: Avg_Satisfaction_Score | M3: Service_Tickets_12M | N3: Competitor_Present | O3: Days_To_Expiry | P3: Account_Manager | Q3: Churn_Drivers | R3: Retention_Action | S3: Cumulative_RaR_AED | T3: Cumulative_Pct_of_RaR
A4: 1 | B4: A00197 | C4: Delta Walters Services FZE | D4: Construction & Contracting | E4: Umm Al Quwain | F4: Platinum | G4: 137 | H4: 12314000 | I4: 81.6 | J4: 10043317 | K4: Critical | L4: 3.71 | M4: 10 | N4: Yes | O4: 150 | P4: Ahmed Siddiqui | Q4: Competitor active in account; High service load (10 tickets); No purchase in 939d; No contact in 109d | R4: ESCALATE: commercial director call within 7 days; service-recovery plan + retention offer on renewal | S4: 10043317 | T4: 1.8
A5: 2 | B5: A00609 | C5: Horizon Anderson Trading LLC | D5: Retail Distribution | E5: Dubai | F5: Platinum | G5: 328 | H5: 10163000 | I5: 90.1 | J5: 9160072 | K5: Critical | L5: 3.61 | M5: 15 | N5: Yes | O5: 324 | P5: Mei Lin Tan | Q5: Competitor active in account; Low satisfaction (3.5/5); High service load (15 tickets); Repeat failures (40%) | R5: ESCALATE: commercial director call within 7 days; service-recovery plan + retention offer on renewal | S5: 19203389 | T5: 3.5
A6: 3 | B6: A00588 | C6: Zenith Lawson Rentals LLC | D6: Logistics & Transport | E6: Ajman | F6: Platinum | G6: 327 | H6: 9224000 | I6: 86 | J6: 7929404 | K6: Critical | L6: 2.34 | M6: 25 | N6: No | O6: 15 | P6: Ahmed Siddiqui | Q6: Low satisfaction (2.4/5); High service load (25 tickets); Repeat failures (80%); No purchase in 648d | R6: ESCALATE: commercial director call within 7 days; service-recovery plan + retention offer on renewal | S6: 27132793 | T6: 5
A7: 4 | B7: A00054 | C7: Cedar Gutierrez Contracting LLC | D7: Retail Distribution | E7: Dubai | F7: Platinum | G7: 365 | H7: 8485000 | I7: 92.6 | J7: 7859789 | K7: Critical | L7: 3.53 | M7: 17 | N7: No | O7: -1034 | P7: Omar Al Farsi | Q7: Low satisfaction (3.4/5); High service load (17 tickets); Repeat failures (29%); No purchase in 831d | R7: ESCALATE: commercial director call within 7 days; service-recovery plan + retention offer on renewal | S7: 34992582 | T7: 6.4
A8: 5 | B8: A00513 | C8: Pearl Washington Services FZE | D8: Construction & Contracting | E8: Ajman | F8: Platinum | G8: 399 | H8: 8745000 | I8: 86 | J8: 7517632 | K8: Critical | L8: 2.19 | M8: 23 | N8: Yes | O8: 1457 | P8: Mei Lin Tan | Q8: Competitor active in account; Low satisfaction (2.0/5); High service load (23 tickets); Repeat failures (39%) | R8: ESCALATE: commercial director call within 7 days; service-recovery plan + retention offer on renewal | S8: 42510214 | T8: 7.8
A9: 6 | B9: A00277 | C9: Delta Flynn Rentals LLC | D9: Hospitality & Tourism | E9: Fujairah | F9: Platinum | G9: 311 | H9: 8098000 | I9: 92.6 | J9: 7501305 | K9: Critical | L9: 3.19 | M9: 18 | N9: Yes | O9: 949 | P9: Rashid Al Mansoori | Q9: Competitor active in account; Low satisfaction (3.1/5); High service load (18 tickets); Repeat failures (56%) | R9: ESCALATE: commercial director call within 7 days; service-recovery plan + retention offer on renewal | S9: 50011519 | T9: 9.1
A10: 7 | B10: A00103 | C10: Al Noor Moreno Holdings | D10: Oil & Gas Services | E10: Dubai | F10: Platinum | G10: 316 | H10: 7480000 | I10: 92.6 | J10: 6928842 | K10: Critical | L10: 3.25 | M10: 17 | N10: Yes | O10: -452 | P10: Elena Petrova | Q10: Competitor active in account; Low satisfaction (3.2/5); High service load (17 tickets); Repeat failures (29%) | R10: ESCALATE: commercial director call within 7 days; service-recovery plan + retention offer on renewal | S10: 56940361 | T10: 10.4
A11: 8 | B11: A00052 | C11: Crescent Rocha Contracting LLC | D11: Oil & Gas Services | E11: Sharjah | F11: Platinum | G11: 183 | H11: 13639000 | I11: 45.4 | J11: 6189131 | K11: Medium | L11: 3.27 | M11: 8 | N11: Yes | O11: -174 | P11: Ahmed Siddiqui | Q11: Competitor active in account; Low satisfaction (3.4/5); Contract expires in -174d | R11: Proactive check-in call + satisfaction survey; monitor at monthly review | S11: 63129492 | T11: 11.5
A12: 9 | B12: A00517 | C12: Delta Garcia Holdings | D12: Construction & Contracting | E12: Dubai | F12: Platinum | G12: 136 | H12: 11964000 | I12: 46.6 | J12: 5572206 | K12: Medium | L12: 2.94 | M12: 13 | N12: Yes | O12: 835 | P12: Daniel Okafor | Q12: Competitor active in account; Low satisfaction (2.7/5); High service load (13 tickets) | R12: Proactive check-in call + satisfaction survey; monitor at monthly review | S12: 68701698 | T12: 12.6
A13: 10 | B13: A00113 | C13: Pearl Hernandez Freight LLC | D13: Logistics & Transport | E13: Dubai | F13: Platinum | G13: 287 | H13: 8694000 | I13: 61.6 | J13: 5352039 | K13: High | L13: 3.43 | M13: 12 | N13: No | O13: -907 | P13: Rashid Al Mansoori | Q13: Low satisfaction (3.1/5); High service load (12 tickets); Repeat failures (33%); No purchase in 454d | R13: Assign named account manager; QBR within 30 days; resolve open service issues before renewal talks | S13: 74053737 | T13: 13.5
A14: 11 | B14: A00129 | C14: Horizon Davis Motors LLC | D14: Retail Distribution | E14: Dubai | F14: Platinum | G14: 79 | H14: 10394000 | I14: 50.3 | J14: 5229997 | K14: High | L14: 3.48 | M14: 7 | N14: No | O14: -113 | P14: Rashid Al Mansoori | Q14: Low satisfaction (3.4/5); Repeat failures (71%); No purchase in 1281d; Contract expires in -113d | R14: Assign named account manager; QBR within 30 days; resolve open service issues before renewal talks | S14: 79283734 | T14: 14.5
A15: 12 | B15: A00263 | C15: Al Noor Long Contracting LLC | D15: Oil & Gas Services | E15: Sharjah | F15: Platinum | G15: 379 | H15: 5537000 | I15: 92.6 | J15: 5129011 | K15: Critical | L15: 3.1 | M15: 18 | N15: Yes | O15: 735 | P15: Daniel Okafor | Q15: Competitor active in account; Low satisfaction (3.3/5); High service load (18 tickets); Repeat failures (28%) | R15: ESCALATE: commercial director call within 7 days; service-recovery plan + retention offer on renewal | S15: 84412745 | T15: 15.4
... A304: 301 | B304: A00696 | C304: Summit Barnes Rentals LLC | D304: Logistics & Transport | E304: Ajman | F304: Bronze | G304: 3 | H304: 74000 | I304: 30 | J304: 22232 | K304: Medium | L304: 4.04 | M304: 2 | N304: No | O304: -346 | P304: Priya Nair | Q304: No purchase in 727d; Contract expires in -346d | R304: Proactive check-in call + satisfaction survey; monitor at monthly review | S304: 459323949 | T304: 84

Sheet Fleet Opportunities
A1: RENEWAL / UPGRADE / CROSS-SELL OPPORTUNITIES - RANKED BY URGENCY
A3: Account_ID | B3: Company_Name | C3: Industry | D3: Emirate | E3: Account_Value_Tier | F3: Fleet_Size | G3: Primary_Product | H3: Annual_Spend_AED | I3: Spend_Growth_Pct | J3: Contract_Expiry | K3: Days_To_Expiry | L3: Last_Purchase_Date | M3: Days_Since_Last_Purchase | N3: Churn_Probability | O3: Risk_Category | P3: Opportunity_Type | Q3: Upgrade_Potential_AED | R3: Urgency_Score | S3: Account_Manager | T3: Recommended_Action
A4: A00588 | B4: Zenith Lawson Rentals LLC | C4: Logistics & Transport | D4: Ajman | E4: Platinum | F4: 327 | G4: Heavy Trucks | H4: 9224000 | I4: 74.8 | J4: 2026-07-15 | K4: 15 | L4: 2024-09-20 | M4: 648 | N4: 86 | O4: Critical | P4: Renewal + Cross-Sell | Q4: 3645786 | R4: 80.1 | S4: Ahmed Siddiqui | T4: URGENT: renewal in 15d on an at-risk account - director-led renewal + service recovery
A5: A00129 | B5: Horizon Davis Motors LLC | C5: Retail Distribution | D5: Dubai | E5: Platinum | F5: 79 | G5: Earth-Moving Equipment | H5: 10394000 | I5: -19.4 | J5: 2026-03-09 | K5: -113 | L5: 2022-12-27 | M5: 1281 | N5: 50.3 | O5: High | P5: Fleet Upgrade | Q5: 5074870 | R5: 75.4 | S5: Rashid Al Mansoori | T5: Pitch fleet refresh - 79 units, last purchase 3y ago; lead with TCO / residual-value case
A6: A00437 | B6: Delta Garcia Facilities LLC | C6: Car Rental & Leasing | D6: Dubai | E6: Gold | F6: 332 | G6: Bus Fleet | H6: 3695000 | I6: 5.5 | J6: 2026-06-29 | K6: -1 | L6: 2023-01-19 | M6: 1258 | N6: 92.6 | O6: Critical | P6: Renewal + Fleet Upgrade | Q6: 3440045 | R6: 71.3 | S6: Mei Lin Tan | T6: URGENT: renewal in -1d on an at-risk account - director-led renewal + service recovery
A7: A00501 | B7: Gulf Beck Group | C7: Construction & Contracting | D7: Sharjah | E7: Gold | F7: 158 | G7: SUV Fleet | H7: 3804000 | I7: -45 | J7: 2026-06-10 | K7: -20 | L7: 2025-02-27 | M7: 488 | N7: 88.4 | O7: Critical | P7: Renewal | Q7: 1021374 | R7: 70.5 | S7: Elena Petrova | T7: URGENT: renewal in -20d on an at-risk account - director-led renewal + service recovery
A8: A00153 | B8: Pearl Mcfarland Contracting LLC | C8: Car Rental & Leasing | D8: Dubai | E8: Platinum | F8: 131 | G8: Bus Fleet | H8: 6281000 | I8: 16.6 | J8: 2025-09-28 | K8: -275 | L8: 2021-09-18 | M8: 1746 | N8: 64.9 | O8: High | P8: Fleet Upgrade | Q8: 3638269 | R8: 70 | S8: Daniel Okafor | T8: Pitch fleet refresh - 131 units, last purchase 4y ago; lead with TCO / residual-value case
A9: A00055 | B9: Marina Hart Transport Co | C9: Retail Distribution | D9: Sharjah | E9: Gold | F9: 291 | G9: SUV Fleet | H9: 2151000 | I9: 5 | J9: 2025-03-06 | K9: -481 | L9: 2021-08-12 | M9: 1783 | N9: 92.6 | O9: Critical | P9: Fleet Upgrade | Q9: 1848247 | R9: 67.9 | S9: Daniel Okafor | T9: Pitch fleet refresh - 291 units, last purchase 4y ago; lead with TCO / residual-value case
A10: A00555 | B10: Marina Reyes Fleet Solutions | C10: Car Rental & Leasing | D10: Fujairah | E10: Gold | F10: 374 | G10: Pickup Fleet | H10: 2171000 | I10: -42 | J10: 2025-01-13 | K10: -533 | L10: 2022-03-25 | M10: 1558 | N10: 92.6 | O10: Critical | P10: Fleet Upgrade | Q10: 2180770 | R10: 67.9 | S10: Omar Al Farsi | T10: Pitch fleet refresh - 374 units, last purchase 4y ago; lead with TCO / residual-value case
A11: A00616 | B11: Summit Townsend Services FZE | C11: Car Rental & Leasing | D11: Sharjah | E11: Gold | F11: 314 | G11: Pickup Fleet | H11: 1910000 | I11: 8.9 | J11: 2026-07-02 | K11: 2 | L11: 2023-09-30 | M11: 1004 | N11: 92.6 | O11: Critical | P11: Renewal | Q11: 736305 | R11: 67.1 | S11: Elena Petrova | T11: URGENT: renewal in 2d on an at-risk account - director-led renewal + service recovery
A12: A00372 | B12: Crescent Rose Transport Co | C12: Construction & Contracting | D12: Fujairah | E12: Gold | F12: 195 | G12: Pickup Fleet | H12: 4221000 | I12: -3.6 | J12: 2023-04-15 | K12: -1172 | L12: 2022-09-01 | M12: 1398 | N12: 64.9 | O12: High | P12: Fleet Upgrade | Q12: 2917766 | R12: 65.5 | S12: Hassan Khoury | T12: Pitch fleet refresh - 195 units, last purchase 3y ago; lead with TCO / residual-value case
A13: A00085 | B13: Falcon Landry Trading LLC | C13: Facilities Management | D13: Sharjah | E13: Platinum | F13: 37 | G13: Earth-Moving Equipment | H13: 5734000 | I13: 32.2 | J13: 2026-04-29 | K13: -62 | L13: 2022-08-31 | M13: 1399 | N13: 47.7 | O13: Medium | P13: Fleet Upgrade | Q13: 2378176 | R13: 64.5 | S13: Hassan Khoury | T13: Pitch fleet refresh - 37 units, last purchase 3y ago; lead with TCO / residual-value case
A14: A00157 | B14: Delta Goodwin Contracting LLC | C14: Facilities Management | D14: Abu Dhabi | E14: Gold | F14: 154 | G14: Heavy Trucks | H14: 4012000 | I14: -45 | J14: 2025-04-30 | K14: -426 | L14: 2022-07-03 | M14: 1458 | N14: 61.6 | O14: High | P14: Fleet Upgrade | Q14: 2485434 | R14: 64.2 | S14: Rashid Al Mansoori | T14: Pitch fleet refresh - 154 units, last purchase 3y ago; lead with TCO / residual-value case
A15: A00351 | B15: Sahara Sullivan Enterprises | C15: Oil & Gas Services | D15: Umm Al Quwain | E15: Silver | F15: 297 | G15: Passenger Sedan Fleet | H15: 1734000 | I15: -15.5 | J15: 2026-08-06 | K15: 37 | L15: 2025-04-17 | M15: 439 | N15: 92.6 | O15: Critical | P15: Renewal | Q15: 646349 | R15: 62.9 | S15: Priya Nair | T15: URGENT: renewal in 37d on an at-risk account - director-led renewal + service recovery
... A177: A00419 | B177: Anchor Carter Equipment LLC | C177: Retail Distribution | D177: Abu Dhabi | E177: Bronze | F177: 11 | G177: Light Commercial Vans | H177: 296000 | I177: 66.3 | J177: 2027-11-02 | K177: 490 | L177: 2026-02-26 | M177: 124 | N177: 5.2 | O177: Low | P177: Cross-Sell | Q177: 46842 | R177: 2 | S177: Omar Al Farsi | T177: Expanding account (+66% YoY) - attach telematics, service contract and finance package

Sheet Pipeline Analytics
A1: SALES PIPELINE ANALYTICS
A3: Funnel - leads reaching each stage
A4: Stage | B4: Leads_Reached | C4: Value_AED | D4: Pct_of_Total | E4: Stage_Conversion_Pct | F4: Drop_Off_Pct | G4: Leads_Lost_At_Stage | H4: Value_Lost_AED
A5: Prospect | B5: 2000 | C5: 6019392000 | D5: 100 | G5: 0 | H5: 0
A6: Qualified | B6: 1751 | C6: 5386231000 | D6: 87.6 | E6: 87.6 | F6: 12.4 | G6: 249 | H6: 633161000
A7: Proposal | B7: 1571 | C7: 4935473000 | D7: 78.6 | E7: 89.7 | F7: 10.3 | G7: 180 | H7: 450758000
A8: Negotiation | B8: 1304 | C8: 4317411000 | D8: 65.2 | E8: 83 | F8: 17 | G8: 267 | H8: 618062000
A9: Won | B9: 608 | C9: 2476918000 | D9: 30.4 | E9: 46.6 | F9: 53.4 | G9: 696 | H9: 1840493000
A12: Open pipeline by stage
A13: Sales_Stage | B13: Deals | C13: Pipeline_AED | D13: Weighted_AED | E13: Stage_Win_Prob_Pct
A14: Prospect | B14: 40 | C14: 85811000 | D14: 8581100 | E14: 10
A15: Qualified | B15: 36 | C15: 105045000 | D15: 26261250 | E15: 25
A16: Proposal | B16: 171 | C16: 395071000 | D16: 177781950 | E16: 45
A17: Negotiation | B17: 133 | C17: 346448000 | D17: 242513600 | E17: 70
A20: Performance by salesperson
A21: Salesperson | B21: Leads | C21: Won_Deals | D21: Lost_Deals | E21: Win_Rate_Pct | F21: Closed_Won_AED | G21: Open_Pipeline_AED | H21: Weighted_Pipeline_AED | I21: Avg_Deal_Size_AED | J21: Avg_Sales_Cycle_Days | K21: Lost_Revenue_AED
A22: Rashid Al Mansoori | B22: 258 | C22: 94 | D22: 116 | E22: 44.8 | F22: 370107000 | G22: 100545000 | H22: 47047650 | I22: 3937308.5 | J22: 63.6 | K22: 292300000
A23: Priya Nair | B23: 291 | C23: 86 | D23: 152 | E23: 36.1 | F23: 362980000 | G23: 142118000 | H23: 78498750 | I23: 4220697.7 | J23: 60.9 | K23: 365956000
A24: Omar Al Farsi | B24: 232 | C24: 86 | D24: 111 | E24: 43.7 | F24: 362971000 | G24: 92213000 | H24: 46453200 | I24: 4220593 | J24: 64 | K24: 267512000
A25: Hassan Khoury | B25: 252 | C25: 72 | D25: 133 | E25: 35.1 | F25: 335890000 | G25: 103427000 | H25: 48422250 | I25: 4665138.9 | J25: 59.7 | K25: 360572000
A26: Daniel Okafor | B26: 272 | C26: 74 | D26: 148 | E26: 33.3 | F26: 328078000 | G26: 144660000 | H26: 69089200 | I26: 4433486.5 | J26: 61.8 | K26: 380193000
A27: Ahmed Siddiqui | B27: 225 | C27: 52 | D27: 125 | E27: 29.4 | F27: 281094000 | G27: 147566000 | H27: 65834450 | I27: 5405653.8 | J27: 59.4 | K27: 337971000
A28: Mei Lin Tan | B28: 240 | C28: 75 | D28: 118 | E28: 38.9 | F28: 241208000 | G28: 71112000 | H28: 29844900 | I28: 3216106.7 | J28: 65.6 | K28: 351725000
A29: Elena Petrova | B29: 230 | C29: 69 | D29: 109 | E29: 38.8 | F29: 194590000 | G29: 130734000 | H29: 69947500 | I29: 2820144.9 | J29: 62.8 | K29: 253870000
A32: Performance by industry
A33: Industry | B33: Leads | C33: Won_Deals | D33: Lost_Deals | E33: Win_Rate_Pct | F33: Closed_Won_AED | G33: Open_Pipeline_AED | H33: Weighted_Pipeline_AED | I33: Avg_Deal_Size_AED | J33: Avg_Sales_Cycle_Days | K33: Lost_Revenue_AED
A34: Construction & Contracting | B34: 343 | C34: 111 | D34: 167 | E34: 39.9 | F34: 578363000 | G34: 171133000 | H34: 84337050 | I34: 5210477.5 | J34: 60.4 | K34: 419331000
A35: Logistics & Transport | B35: 408 | C35: 140 | D35: 192 | E35: 42.2 | F35: 539472000 | G35: 188586000 | H35: 103427750 | I35: 3853371.4 | J35: 62 | K35: 563603000
A36: Car Rental & Leasing | B36: 292 | C36: 88 | D36: 150 | E36: 37 | F36: 288618000 | G36: 117748000 | H36: 54494800 | I36: 3279750 | J36: 66 | K36: 365390000
A37: Oil & Gas Services | B37: 205 | C37: 64 | D37: 107 | E37: 37.4 | F37: 238837000 | G37: 86196000 | H37: 38977700 | I37: 3731828.1 | J37: 59.9 | K37: 254840000
A38: Facilities Management | B38: 202 | C38: 60 | D38: 97 | E38: 38.2 | F38: 224588000 | G38: 84323000 | H38: 39208200 | I38: 3743133.3 | J38: 64.8 | K38: 300964000
A39: Hospitality & Tourism | B39: 171 | C39: 43 | D39: 101 | E39: 29.9 | F39: 212221000 | G39: 60113000 | H39: 29581850 | I39: 4935372.1 | J39: 64 | K39: 193194000
A40: Retail Distribution | B40: 215 | C40: 57 | D40: 118 | E40: 32.6 | F40: 209030000 | G40: 129027000 | H40: 59201850 | I40: 3667193 | J40: 62 | K40: 308702000
A41: Government & Municipal | B41: 164 | C41: 45 | D41: 80 | E41: 36 | F41: 185789000 | G41: 95249000 | H41: 45908700 | I41: 4128644.4 | J41: 61 | K41: 204075000
A44: Performance by emirate
A45: Emirate | B45: Leads | C45: Won_Deals | D45: Lost_Deals | E45: Win_Rate_Pct | F45: Closed_Won_AED | G45: Open_Pipeline_AED | H45: Weighted_Pipeline_AED | I45: Avg_Deal_Size_AED | J45: Avg_Sales_Cycle_Days | K45: Lost_Revenue_AED
A46: Dubai | B46: 657 | C46: 201 | D46: 328 | E46: 38 | F46: 858971000 | G46: 293505000 | H46: 138161900 | I46: 4273487.6 | J46: 61.4 | K46: 856931000
A47: Abu Dhabi | B47: 501 | C47: 152 | D47: 258 | E47: 37.1 | F47: 600306000 | G47: 226293000 | H47: 104701100 | I47: 3949381.6 | J47: 65.2 | K47: 667417000
A48: Sharjah | B48: 360 | C48: 105 | D48: 186 | E48: 36.1 | F48: 404982000 | G48: 211668000 | H48: 110690700 | I48: 3856971.4 | J48: 60.7 | K48: 462746000
A49: Ajman | B49: 156 | C49: 49 | D49: 76 | E49: 39.2 | F49: 216404000 | G49: 61575000 | H49: 30894850 | I49: 4416408.2 | J49: 63 | K49: 227148000
A50: Ras Al Khaimah | B50: 139 | C50: 45 | D50: 72 | E50: 38.5 | F50: 171941000 | G50: 44666000 | H50: 22551900 | I50: 3820911.1 | J50: 59.9 | K50: 227218000
A51: Umm Al Quwain | B51: 90 | C51: 31 | D51: 43 | E51: 41.9 | F51: 121156000 | G51: 42823000 | H51: 23725500 | I51: 3908258.1 | J51: 65.7 | K51: 87176000
A52: Fujairah | B52: 97 | C52: 25 | D52: 49 | E52: 33.8 | F52: 103158000 | G52: 51845000 | H52: 24411950 | I52: 4126320 | J52: 59.7 | K52: 81463000
A55: Lost-deal analysis
A56: Lost_Reason | B56: Deals | C56: Revenue_Lost_AED | D56: Pct_of_Lost_Revenue
A57: Price / Budget | B57: 304 | C57: 783434000 | D57: 30
A58: Competitor Won | B58: 259 | C58: 710611000 | D58: 27.2
A59: No Decision / Stalled | B59: 209 | C59: 547350000 | D59: 21
A60: Timing Deferred | B60: 144 | C60: 345713000 | D60: 13.2
A61: Spec Mismatch | B61: 96 | C61: 222991000 | D61: 8.5

Sheet Marketing Analytics
A1: LEAD SOURCE PERFORMANCE & MARKETING EFFICIENCY
A3: Lead_Source | B3: Lead_Volume | C3: Qualified_Plus | D3: Won_Deals | E3: Conversion_Rate_Pct | F3: Revenue_AED | G3: Avg_Deal_Value_AED | H3: Open_Pipeline_AED | I3: Avg_Lead_Score | J3: Lead_Quality_Pct | K3: Cost_per_Lead_USD | L3: Total_Spend_USD | M3: Cost_per_Acquisition_USD | N3: Gross_Margin_USD | O3: ROI_Pct | P3: Margin_Return_per_USD | Q3: Revenue_Share_Pct
A4: LinkedIn | B4: 496 | C4: 432 | D4: 128 | E4: 25.8 | F4: 517001000 | G4: 4039070.3 | H4: 219899000 | I4: 41 | J4: 87.1 | K4: 50 | L4: 24800 | M4: 194 | N4: 16893157 | O4: 68018 | P4: 681.2 | Q4: 20.9
A5: Referral | B5: 230 | C5: 212 | D5: 131 | E5: 57 | F5: 461132000 | G5: 3520091.6 | H5: 34579000 | I5: 67.9 | J5: 92.2 | K5: 0 | L5: 0 | M5: 0 | N5: 15067622 | Q5: 18.6
A6: Website | B6: 369 | C6: 307 | D6: 80 | E6: 21.7 | F6: 422672000 | G6: 5283400 | H6: 208366000 | I6: 35.9 | J6: 83.2 | K6: 20 | L6: 7380 | M6: 92 | N6: 13810930 | O6: 187040 | P6: 1871.4 | Q6: 17.1
A7: Trade Shows | B7: 265 | C7: 242 | D7: 113 | E7: 42.6 | F7: 417951000 | G7: 3698681.4 | H7: 66393000 | I7: 56.9 | J7: 91.3 | K7: 200 | L7: 53000 | M7: 469 | N7: 13656670 | O7: 25667 | P7: 257.7 | Q7: 16.9
A8: Partners | B8: 185 | C8: 171 | D8: 86 | E8: 46.5 | F8: 342484000 | G8: 3982372.1 | H8: 109239000 | I8: 63.3 | J8: 92.4 | K8: 30 | L8: 5550 | M8: 65 | N8: 11190764 | O8: 201535 | P8: 2016.4 | Q8: 13.8
A9: Email | B9: 271 | C9: 227 | D9: 47 | E9: 17.3 | F9: 186699000 | G9: 3972319.1 | H9: 163085000 | I9: 33.1 | J9: 83.8 | K9: 15 | L9: 4065 | M9: 86 | N9: 6100444 | O9: 149972 | P9: 1500.7 | Q9: 7.5
A10: Outbound | B10: 184 | C10: 160 | D10: 23 | E10: 12.5 | F10: 128979000 | G10: 5607782.6 | H10: 130814000 | I10: 22.7 | J10: 87 | K10: 40 | L10: 7360 | M10: 320 | N10: 4214426 | O10: 57161 | P10: 572.6 | Q10: 5.2
A12: ROI is computed on a 12% assumed gross margin. Referral carries no media cost, so its ROI is undefined (n/a) - judge it on conversion rate and average deal size. CAVEAT: the prescribed cost-per-lead figures are nominal digital-marketing rates while the deals are enterprise fleet orders, so absolute ROI percentages are implausibly large. Use them to RANK channels against each other, not as a budget forecast.

Sheet Model Performance
A1: MODEL PERFORMANCE - HELD-OUT TEST SET (ACTUAL SCIKIT-LEARN OUTPUT)
A3: Task | B3: Model | C3: Champion | D3: Accuracy | E3: Precision | F3: Recall | G3: F1 | H3: ROC_AUC_Test | I3: ROC_AUC_Train | J3: CV_ROC_AUC_Mean | K3: CV_Std | L3: n_train | M3: n_test
A4: Lead Scoring | B4: Logistic Regression | C4: YES | D4: 0.758 | E4: 0.655 | F4: 0.75 | G4: 0.699 | H4: 0.824 | I4: 0.824 | J4: 0.804 | K4: 0.023 | L4: 1215 | M4: 405
A5: Lead Scoring | B5: Random Forest | D5: 0.746 | E5: 0.648 | F5: 0.704 | G5: 0.675 | H5: 0.813 | I5: 0.864 | J5: 0.793 | K5: 0.02 | L5: 1215 | M5: 405
A6: Churn | B6: Logistic Regression | D6: 0.689 | E6: 0.487 | F6: 0.704 | G6: 0.576 | H6: 0.737 | I6: 0.833 | J6: 0.761 | K6: 0.031 | L6: 540 | M6: 180
A7: Churn | B7: Random Forest | C7: YES | D7: 0.683 | E7: 0.478 | F7: 0.593 | G7: 0.529 | H7: 0.737 | I7: 0.925 | J7: 0.759 | K7: 0.035 | L7: 540 | M7: 180
A10: Confusion matrices (test set)
A11: Task | B11: Model | C11: True_Negative | D11: False_Positive | E11: False_Negative | F11: True_Positive | G11: Precision_Check | H11: Recall_Check
A12: Lead Scoring | B12: Logistic Regression | C12: 193 | D12: 60 | E12: 38 | F12: 114 | G12: 0.655 | H12: 0.75
A13: Lead Scoring | B13: Random Forest | C13: 195 | D13: 58 | E13: 45 | F13: 107 | G13: 0.648 | H13: 0.704
A14: Churn | B14: Logistic Regression | C14: 86 | D14: 40 | E14: 16 | F14: 38 | G14: 0.487 | H14: 0.704
A15: Churn | B15: Random Forest | C15: 91 | D15: 35 | E15: 22 | F15: 32 | G15: 0.478 | H15: 0.593
A18: Lead scoring - top 15 feature drivers | E18: Churn - top 15 feature drivers
A19: Feature | B19: RF_Importance | C19: LR_Coefficient | E19: Feature | F19: RF_Importance | G19: LR_Coefficient
A20: Budget_Allocated_Yes | B20: 0.1562 | C20: 0.6553 | E20: Days_Since_Last_Purchase | F20: 0.2078 | G20: 0.9096
A21: Budget_Allocated_No | B21: 0.1431 | C21: -0.7928 | E21: Srv_Avg_Sat | F21: 0.1007 | G21: -0.3176
A22: Days_in_Pipeline | B22: 0.1091 | C22: -0.4394 | E22: Fleet_Size | F22: 0.0822 | G22: 0.3076
A23: Deal_Value_AED | B23: 0.0962 | C23: 0.0671 | E23: Srv_Cost | F23: 0.0645 | G23: -0.0319
A24: Fleet_Size | B24: 0.0825 | C24: 0.1095 | E24: Srv_Tickets | F24: 0.0577 | G24: 0.3769
A25: Units_Requested | B25: 0.0691 | C25: 0.1059 | E25: Srv_Min_Sat | F25: 0.0467 | G25: -0.0441
A26: Number_of_Sales_Calls | B26: 0.0635 | C26: 0.1997 | E26: Annual_Spend_AED | F26: 0.0465 | G26: -0.3607
A27: Days_Since_Last_Contact | B27: 0.0551 | C27: -0.2046 | E27: Spend_Growth_Pct | F27: 0.0437 | G27: -0.0801
A28: Lead_Source_Referral | B28: 0.0351 | C28: 1.0399 | E28: Days_Since_Last_Activity | F28: 0.0421 | G28: 0.1571
A29: Company_Size_Small (<50) | B29: 0.018 | C29: -0.5804 | E29: Competitor_Present_Yes | F29: 0.0413 | G29: 0.5075
A30: Company_Size_Enterprise (1000+) | B30: 0.0164 | C30: 0.5306 | E30: Competitor_Present_No | F30: 0.0409 | G30: -0.5139
A31: Lead_Source_Outbound | B31: 0.0142 | C31: -1.0953 | E31: Srv_Avg_Res | F31: 0.0385 | G31: 0.0597
... A34: Company_Size_Large (250-999) | B34: 0.0101 | C34: 0.1829 | E34: Srv_Repeat | F34: 0.0286 | G34: 0.0686
A37: Interpretation: train ROC-AUC close to test ROC-AUC indicates the model is not overfitting. For churn, recall is prioritised over precision - missing a leaver costs far more than an unnecessary retention call.

Sheet Executive Dashboard
A1: EXECUTIVE DASHBOARD - UAE FLEET SALES INTELLIGENCE (SYNTHETIC DATA)
A2: As-of 30 Jun 2026 | AED unless stated | KPI cards are live formulas over the raw and analysis sheets
A4: CLOSED-WON REVENUE | D4: RECURRING BASE REVENUE | G4: OPEN PIPELINE | J4: WEIGHTED PIPELINE
A5: =SUMIFS('Leads Raw'!K2:K2001,'Leads Raw'!L2:L2001,"Won") -> 2476918000 | D5: =SUM('Churn Prediction'!G2:G721) -> 1429525000 | G5: =SUMIFS('Leads Raw'!K2:K2001,'Leads Raw'!L2:L2001,"<>Won",'Leads Raw'!L2:L2001,"<>Lost") -> 932375000 | J5: =SUM('Pipeline Analytics'!D14:D17) -> 455137900
A7: WIN RATE % | D7: LEAD CONVERSION % | G7: HIGH-PRIORITY OPEN LEADS | J7: REVENUE AT RISK
A8: =ROUND(COUNTIF('Leads Raw'!L2:L2001,"Won")/(COUNTIF('Leads Raw'!L2:L2001,"Won")+COUNTIF('Leads Raw'!L2:L2001,"Lost"))*100,1) -> 37.5 | D8: =ROUND(COUNTIF('Leads Raw'!L2:L2001,"Won")/2000*100,1) -> 30.4 | G8: =COUNTIFS('Lead Scoring'!Q2:Q2001,"Very High",'Lead Scoring'!K2:K2001,"<>Won",'Lead Scoring'!K2:K2001,"<>Lost") -> 80 | J8: =SUM('Churn Prediction'!P2:P721) -> 546708897
A10: HIGH-RISK ACCOUNTS | D10: RENEWAL OPPORTUNITIES | G10: UPGRADE OPPORTUNITIES | J10: OPPORTUNITY VALUE
A11: =COUNTIF('Churn Prediction'!O2:O721,"Critical")+COUNTIF('Churn Prediction'!O2:O721,"High") -> 158 | D11: =COUNTIF('Fleet Opportunities'!P4:P177,"*Renewal*") -> 51 | G11: =COUNTIF('Fleet Opportunities'!P4:P177,"*Upgrade*") -> 60 | J11: =SUM('Fleet Opportunities'!Q4:Q177) -> 125856379
A15: CHART DATA (linked to the analysis sheets)
A16: Stage | B16: Leads_Reached | D16: Industry | E16: Annual_Revenue_AED | F16: Revenue_at_Risk_AED | H16: Lead_Source | I16: Revenue_AED | J16: Lead_Volume | L16: Sales_Stage | M16: Pipeline_AED | N16: Weighted_AED | P16: Company_Name | Q16: Revenue_at_Risk_AED | S16: Risk_Category | T16: Accounts
A17: Prospect | B17: 2000 | D17: Logistics & Transport | E17: 278175000 | F17: 101488903 | H17: LinkedIn | I17: 517001000 | J17: 496 | L17: Prospect | M17: 85811000 | N17: 8581100 | P17: Delta Walters Services FZE | Q17: 10043317 | S17: Critical | T17: 47
A18: Qualified | B18: 1751 | D18: Construction & Contracting | E18: 265252000 | F18: 116501132 | H18: Referral | I18: 461132000 | J18: 230 | L18: Qualified | M18: 105045000 | N18: 26261250 | P18: Horizon Anderson Trading LLC | Q18: 9160072 | S18: High | T18: 111
A19: Proposal | B19: 1571 | D19: Oil & Gas Services | E19: 180219000 | F19: 66180041 | H19: Website | I19: 422672000 | J19: 369 | L19: Proposal | M19: 395071000 | N19: 177781950 | P19: Zenith Lawson Rentals LLC | Q19: 7929404 | S19: Medium | T19: 143
A20: Negotiation | B20: 1304 | D20: Retail Distribution | E20: 176969000 | F20: 76260260 | H20: Trade Shows | I20: 417951000 | J20: 265 | L20: Negotiation | M20: 346448000 | N20: 242513600 | P20: Cedar Gutierrez Contracting LLC | Q20: 7859789 | S20: Low | T20: 419
A21: Won | B21: 608 | D21: Car Rental & Leasing | E21: 173119000 | F21: 55543323 | H21: Partners | I21: 342484000 | J21: 185 | P21: Pearl Washington Services FZE | Q21: 7517632
D22: Facilities Management | E22: 136316000 | F22: 48753531 | H22: Email | I22: 186699000 | J22: 271 | P22: Delta Flynn Rentals LLC | Q22: 7501305
D23: Hospitality & Tourism | E23: 111183000 | F23: 41680769 | H23: Outbound | I23: 128979000 | J23: 184 | P23: Al Noor Moreno Holdings | Q23: 6928842
D24: Government & Municipal | E24: 108292000 | F24: 40325346 | P24: Crescent Rocha Contracting LLC | Q24: 6189131
P25: Delta Garcia Holdings | Q25: 5572206
P26: Pearl Hernandez Freight LLC | Q26: 5352039
